Workbook

Sheet Overview
A1: Twenty-Five Untapped Opportunities
A2: Research date: 2 August 2026 · 15 discovery lenses · 172 raw candidates · 77 distinct opportunities · 25 selected
A4: READ THIS FIRST
A5: The session's 200-call web-search budget was exhausted partway through this study.
A6: Every finding carries an evidence tier recording what its competitor check was actually worth.
A7: The adversarial verification pass ran with ZERO live searches, so its objections are recorded as open
A8: diligence questions, never as verdicts. The planned "refuted by both lenses = disqualified" rule was
A9: abandoned for that reason - applying it would have deleted the pool on an unusable measurement.
A11: The tier rates the COMPETITOR CHECK, not the discovery. The scout stage ran 41-84 live queries per lens
A12: before the budget died, so the "why now" triggers generally rest on real search results. On a Recall-only
A13: finding, trust the trigger considerably more than the claim that the space is empty.
A15: Evidence tiers
A16: Tier | B16: In top 25 | C16: In full pool | D16: Meaning
A17: Search-backed | B17: =COUNTIF('Top 25'!$E:$E,$A17) | C17: =COUNTIF('Screening Scores'!$C:$C,$A17) | D17: Crowding checked with roughly 30 live competitor queries
A18: Thin | B18: =COUNTIF('Top 25'!$E:$E,$A18) | C18: =COUNTIF('Screening Scores'!$C:$C,$A18) | D18: Only 2-3 live queries before the search budget ran out
A19: Recall-only | B19: =COUNTIF('Top 25'!$E:$E,$A19) | C19: =COUNTIF('Screening Scores'!$C:$C,$A19) | D19: No live crowding search; competitors named from model recall
A20: Total | B20: =SUM(B17:B19) | C20: =SUM(C17:C19)
A22: Scoring weights | B22: Edit the yellow cells to re-rank the whole workbook
A23: Dimension | B23: Weight | C23: Meaning of a 10
A24: Overlooked | B24: 0.28 | C24: Essentially nobody is building this, verified by search
A25: Inflection (3-5 yr) | B25: 0.24 | C25: Near-certain to be a large market by 2029-2031
A26: Buildable today | B26: 0.2 | C26: A 1-3 person team ships a real wedge in 90 days
A27: Market size | B27: 0.16 | C27: Multi-billion addressable
A28: Defensibility | B28: 0.12 | C28: Strong compounding moat
A29: Total | B29: =SUM(B24:B28) | C29: Must equal 1.00
A31: Sheets in this workbook
A32: Top 25 | B32: The ranked selection, with scores, evidence tier and selection rationale
A33: All Opportunities | B33: All 77 distinct opportunities that survived de-duplication
A34: Screening Scores | B34: Every screening score, competitor check and kill risk
A35: Verification | B35: Adversarial objections - open questions, not verdicts
A36: Honorable Mentions | B36: The 12 that just missed the cut
A38: Source: research/dataset.json in this repository; see research/METHODOLOGY.md for the full pipeline and coverage limitations. Composite scores on every sheet are live formulas driven by the yellow weight cells above, so changing a weight re-scores all 77 opportunities at once. Data note: one screening agent recorded a composite of 4.92 for "rec-e-invoicing-mandate-plumbing-for-us-mid-market-erps" where the stated weights give 4.64. The workbook computes every composite from the weights, so it shows the corrected 4.64. That opportunity was not in the top 25, so the selection is unaffected. All 76 other composites reproduce exactly. Build note: LibreOffice is non-functional in the environment that produced this file, so formulas were written without cached values and could not be machine-recalculated. Recalculate-on-load is set, and every formula uses only SUM, ROUND, COUNTIF, INDEX, MATCH and IFERROR. If any cell looks blank, press Ctrl-Alt-F9.

Sheet Top 25
A1: Rank | B1: Opportunity | C1: Category | D1: ID | E1: Evidence | F1: Overlooked | G1: Inflection | H1: Buildable | I1: Market | J1: Defensibility | K1: Composite | L1: The wedge | M1: Why this rank | N1: What kills it | O1: Open questions from adversarial review
A2: 1 | B2: Ride-through models and curtailment proof for NERC-registered data centers | C2: Physical / industrial | D2: datacenter-as-grid-entity-compliance | E2: Recall-only | F2: 5 | G2: 8 | H2: 7 | I2: 6 | J2: 5 | K2: =ROUND(F2*Overview!$B$24+G2*Overview!$B$25+H2*Overview!$B$26+I2*Overview!$B$27+J2*Overview!$B$28,2) | L2: Boutique that builds the filed dynamic model (EPRI UDM/CMLD), runs disturbance-response testing on UPS/rectifier/chiller settings, and assembles the NERC attestation package per campus at $150k-$600k, plus the signed metering record proving each ERCOT curtailment. | M2: Best risk-adjusted bet in the pool: four dated triggers have ALREADY fired (NERC Level 3 Alert 4 May 2026 with responses due 3 Aug 2026 — literally this week; FERC RD26-7 ordering mandatory computational-load standards by 31 Dec 2026; RM26-4 §206 orders to every RTO 18 Jun 2026), so revenue exists in month one rather than after a rule lands. No license gate, no capital, no enterprise sales cycle — the buyer is under an enforcement clock. Two or three power-systems engineers can start Monday. Re-validation after every trip event makes it recurring, and ERCOT PCLR registration is a second product on the same relationship. Overlooked only scored 5 because Certrec, 1898 & Co and Burns & McDonnell can pivot — but those firms are capacity-constrained and the specific artifact (validated EMT models for power-electronic compute load) is new to everyone, so the head start is real. Ranked above nuclear and customs because it needs no exam, no ACE certification, and no three-year audit history before the first invoice. | N2: It is a boutique engineering consultancy, not a compounding software company. The binding constraint is one or two humans who can translate IEC 62040-3 UPS transfer behavior into an ISO-acceptable load model, and those people are the scarcest labor in the sector — Burns & McDonnell, Certrec and POWER already hold the hyperscaler relationships and can hire them away or simply out-bench you. Revenue scales linearly with headcount, the 'reusable model library' is mostly customer-confidential, and the natural exit is acquisition by an EPC at services multiples rather than a durable platform. | O2: Not selected for verification
A3: 2 | B3: Entry Type 13 and instrument-aware duty recovery for the post-de-minimis long tail | C3: Regulatory clock | D3: long-tail-customs-entry-and-duty-recovery | E3: Recall-only | F3: 4 | G3: 8 | H3: 6 | I3: 8 | J3: 6 | K3: =ROUND(F3*Overview!$B$24+G3*Overview!$B$25+H3*Overview!$B$26+I3*Overview!$B$27+J3*Overview!$B$28,2) | L3: Software letting one licensed broker supervise 50-100x entry throughput on low-value shipments, sold as entry-as-a-service to SMB importers, bolted to instrument-aware drawback recovery (Section 301 eligible, Section 232 generally not). | M3: The only genuine compounding regulatory moat in the entire 77: a licensed profession with exam-gated supply (12-22% pass rate) meeting a legislated ~100x volume shock (1.36B FY2024 de minimis parcels), where the license, the bond and the accumulated per-SKU ruling corpus all compound and none can be cloned by a software competitor. The statutory spine is the hardest in the pool — OBBBA permanently repeals the commercial de minimis statute effective 1 Jul 2027, which no executive action reverses — and the duty-recovery half is the single most credible 'LLMs newly make this cheap' claim here because it is legal-grade reasoning over structured data with a dollar-denominated output. Ranked 2 not 1 on two real drags: ACE/ABI certification is a 6-12 month regulatory slog outside the 90-day frame, and Zonos (~$69M, already licensed and filing automated low-value entries) can move down-market faster than a new entrant acquires the tail. Entry Type 13 and the 22 Sep 2026 ACE test are unverified and load-bearing — diligence before capital. | N3: Unit economics on the exact segment being targeted. A $500 shipment cannot carry compliant entry work at any price — that is why 3PLs are turning these accounts away, and software does not repeal it; at $15/entry you need enormous volume before you cover the classification labor, while carrying 19 CFR 111 broker penalty and license exposure on SKUs you have never seen. Meanwhile the parcel carriers (DHL, UPS, FedEx) own the flow and built their own de minimis replacement entry services, and Zonos can move down-market faster than you can acquire the long tail. Secondary risk: the ACE ABI certification gate is a 6-12 month regulatory slog, not part of a 90-day plan. Offsetting all this, and why this one advances — a licensed profession with a hard exam-gated supply constraint meeting a legislated ~100x volume shock is a genuine dislocation, the license plus bond plus accumulated per-SKU ruling corpus is the only real compounding regulatory moat in this batch, and instrument-aware planning is the single most credible 'LLMs newly make this cheap' argument here because it is legal-grade reasoning over structured data with a dollar-denominated output. | O3: Not selected for verification
A4: 3 | B4: NQA-1 qualification and commercial grade dedication as a service | C4: Physical / industrial | D4: nuclear-naval-supplier-qualification | E4: Recall-only | F4: 6 | G4: 7 | H4: 8 | I4: 5 | J4: 6 | K4: =ROUND(F4*Overview!$B$24+G4*Overview!$B$25+H4*Overview!$B$26+I4*Overview!$B$27+J4*Overview!$B$28,2) | L4: Fixed-fee turnkey installation of an Appendix B / NQA-1 quality system into existing AS9100 shops, plus an outsourced dedicating-entity service with a structured critical-characteristics library for commercial grade dedication. | M4: Highest round-1 composite (6.48) and the bottleneck is correctly identified: qualification, not capital or reactor design, gates both the nuclear build-out and the submarine industrial base, and NUPIC is a closed utility club new entrants structurally cannot join. Demand broke the chicken-and-egg deadlock in 2025-2026 via hyperscaler PPAs and the ADVANCE Act, and the 17,000-to-~5,000 submarine supplier contraction plus BlueForge's ~$950M NAVSEA award are real. Held to 3 by the screener's correct kill: this is a consulting business wearing software clothes. Critical characteristics are treated as proprietary and litigation-sensitive, so the cross-buyer reusable library — the entire software thesis — may never accrete, leaving hourly-consulting margins against Curtiss-Wright/Scientech and Paragon, who already operate as third-party dedicating entities with audit histories you would spend three years earning. Still advances because even the consulting version is a real, defensible, high-margin business against a hard supply constraint. | N4: It is a consulting business wearing software clothes. CGD packages are bespoke and liability-bearing, and utilities, reactor developers and their suppliers treat critical characteristics as proprietary and litigation-sensitive — so the cross-buyer reusable library never accretes, margins stay at hourly-consulting levels, and Curtiss-Wright or Paragon bolt a workflow tool onto a book of business and a dedicating-entity audit history you spent three years earning. | O4: Not selected for verification
A5: 4 | B5: PFAS-Compliant Biosolids Outlet Exchange for the Mid-Atlantic | C5: Physical / industrial | D5: biosolids-outlet-exchange | E5: Search-backed | F5: 5 | G5: 7 | H5: 8 | I5: 5 | J5: 4 | K5: =ROUND(F5*Overview!$B$24+G5*Overview!$B$25+H5*Overview!$B$26+I5*Overview!$B$27+J5*Overview!$B$28,2) | L5: Regional brokerage contracting landfill airspace, thermal destruction slots and compliant out-of-state farmland, matched against each POTW's tonnage and PFAS test results at a firm per-wet-ton price with documentation attached; second product is upstream industrial source control. | M5: Survived adversarial verification 1-of-2, and the surviving lens confirmed the strongest-verified trigger in its batch: Maryland SB 719 signed 28 April 2026 banning land application at or above 50 ppb PFOA/PFOS from 1 Oct 2028, a 25-50 ppb restricted tier, plus Maine, Connecticut and six 2026 enactments and EPA's 1 July 2026 draft guidance. Crucially the mechanism already ran once for real — Maine's LD 1911 produced exactly the predicted out-of-state trucking and tipping-cost spike — so this is not a forecast. Capital-light, no capex, and the buyer is a rate-funded public utility that must move wet tons daily and has clear procurement authority. Ranked 4 rather than higher because the refuting lens is right that Synagro (Goldman-backed) and Denali (PE-backed) hold long-term contracts, bonding and the trucks, and municipal RFPs demand performance bonds and referenceable tonnage a two-person broker lacks; PFAS liability on land application is also increasingly uninsurable. Wedge in as the analyst who knows which outlet accepts which concentration this quarter, then earn the tonnage. | N5: Defensibility is the weak leg: non-exclusive outlet contracts, zero capex, and no proprietary data mean Synagro or Denali can match any quoted per-wet-ton price and bundle the hauling you do not own. The 'knowing which outlet accepts which concentration this quarter' edge is a decaying asset — once state thresholds stabilize (MD's are already written into statute with numbers), the arbitrage compresses. Landfill airspace is the substitution risk in the other direction: Maryland/Maine reporting already flags landfill capacity concerns, so the outlets you forward-contract may themselves be closed to biosolids by state action. Market size is modest — US biosolids management is single-digit billions of total spend and a Mid-Atlantic broker's take rate is a thin slice of that. Working capital risk if you sign firm per-ton prices against outlet costs that reprice. | O5: [lens] The 'regional biosolids outlet brokerage' is the existing business model of large, capitalized, vertically integrated incumbents — Synagro (the largest US biosolids manager, Goldman Sachs Infrastructure-owned), Denali Water Solutions (TPG-backed), and Merrell Bros. — who already contract POTW tonnage, own or contract landfill/incineration/land-application outlets, run the trucks, and have been selling PFAS-transition planning as their headline service since the EPA risk assessment. The regulatory-analysis layer ('which outlet accepts which concentration under which state rule this quarter') is the core 2025-2026 consulting product of Brown and Caldwell, Hazen and Sawyer, Arcadis, CDM Smith, Black & Veatch and Stantec, all of whom run biosolids master-planning practices. A two-person no-capex broker has neither outlet access nor bonding nor the balance sheet to offer a firm per-wet-ton price. [lens] Not the trigger — the trigger holds — but the seat at the table. This market is already consolidated and contracted: Synagro (the largest US biosolids manager, Goldman Sachs West Street-backed), Casella Organics (which does precisely regional POTW outlet brokerage across New England and the Mid-Atlantic, including absorbing Maine's post-ban volume), Denali Water Solutions, Merrell Bros., Quantix and the landfill majors already hold the landfill airspace, the dryers, the incinerator slots and the multi-year municipal contracts. 'Two operators, no capital equipment' cannot sign non-exclusive outlet capacity that the incumbents have under long-term take-or-pay, and cannot win the POTW side either: municipal biosolids hauling is procured by public RFP requiring performance bonds, insurance minimums, state hauler/land-application permits and referenceable tonnage history. The PFAS liability exposure is the second knife — routing sludge to farmland is the exact act being litigated (Maine farms, the Johnson County, Texas suits against a biosolids applier), and PFAS is being excluded from environmental liability policies, so an unbonded intermediary is uninsurable in the one transaction it exists to broker. Landfills are also closing to sludge over leachate PFAS, so the 'outlet' inventory being brokered is shrinking rather than expanding.
A6: 5 | B6: Reachability-grade SBOMs and kernel-CVE triage for embedded Linux | C6: Regulatory clock | D6: cra-embedded-sbom-and-cve-triage | E6: Recall-only | F6: 3 | G6: 8 | H6: 6 | I6: 7 | J6: 6 | K6: =ROUND(F6*Overview!$B$24+G6*Overview!$B$25+H6*Overview!$B$26+I6*Overview!$B$27+J6*Overview!$B$28,2) | L6: Ingest a Yocto/Buildroot/PetaLinux build or raw firmware, emit an SBOM scoring clean against BSI TR-03183-2, index reachability from the kernel .config and driver set, and run it daily against the kernel CNA feed to produce ranked affects-you/does-not lists with OpenVEX justifications. | M6: The recurring pain is correctly located — the CRA's expensive cost is not writing an SBOM, it is deciding weekly whether this week's CVEs reach a shipped device and proving it to a market surveillance authority. Technical why_now verified: the Linux kernel CNA floods ~50 unscored CVEs/week and LTS support contracted from six years to two, while Art. 14 reporting starts 11 Sep 2026 on products already on the market and full CE marking lands 11 Dec 2027. This is a maintenance-contract shape, not a one-time audit, which is the right revenue geometry. Drags that keep it at 5: distribution belongs to whoever ships the BSP — Timesys Vigiles (now Lynx) does config-aware kernel CVE triage today and Qualcomm/Foundries.io bundles continuous remediation with the subscription the customer already buys — and the 90-day two-person plan badly understates binary SBOM extraction plus .config reachability indexing at defensible quality. | N6: Distribution is owned by whoever already ships the BSP. The SoC vendor, Timesys/Lynx, Wind River or Qualcomm/Foundries bundles CVE triage with the board support package the customer is already paying for, so you are selling an add-on against something included. The 90-day two-person plan also badly understates the work — kernel .config reachability indexing plus SBOM extraction from raw firmware binaries is a multi-year engineering problem to do at defensible quality, not a quarter. And the VEX justification you emit is a legal assertion the customer must sign; if a market surveillance authority rejects 'subsystem not compiled in,' your core output is worthless. | O6: Not selected for verification
A7: 6 | B7: Funded-Claim Detection for Casualty Reserving | C7: Boring vertical | D7: funded-claim-detection-for-casualty | E7: Search-backed | F7: 6 | G7: 6 | H7: 6 | I7: 5 | J7: 6 | K7: =ROUND(F7*Overview!$B$24+G7*Overview!$B$25+H7*Overview!$B$26+I7*Overview!$B$27+J7*Overview!$B$28,2) | L7: Claim-scoring data utility fusing the newly public litigation-funder registries with docket data, UCC-1 filings, plaintiff-firm network graphs and medical-lien patterns to flag probable funder involvement at first notice of loss. | M7: Survived adversarial verification 1-of-2, and the surviving lens made the point that matters most under a buyer test: the sufferer IS the payer. Carriers and reinsurers absorb adverse development directly, claims analytics and reserving are established budget lines, and social inflation is the single most-cited casualty concern — willingness to pay is not speculative. The raw material genuinely did not exist before 2026 (Georgia's NMLS registration commenced 1 Jan 2026 with 5% beneficial-ownership disclosure; West Virginia, Indiana, Louisiana, Montana all added regimes), and the Law.com 17 Jul 2026 open-records piece supports that no vendor had assembled the list. Held to 6 by two real problems the screener named: consumer pre-settlement advances to individual plaintiffs are generally not UCC-1 perfected, so the cross-join likely resolves firm-level portfolio funding rather than the per-claim signal being sold; and the disclosure wave that creates the data also erodes the need for inference by 2028-29. Sell the quarterly funder-intelligence report first, productize scoring only once linkage is proven. | N7: The thesis is self-cannibalizing. The same disclosure wave that creates the raw material also destroys the need for detection — Georgia, Kansas, Indiana, Louisiana, Montana, West Virginia and Wisconsin already mandate funder-identity disclosure, ISO has approved a Litigation Funding Disclosure Condition endorsement, and S.3826 would federalize it for class actions and MDLs. If disclosure becomes routine by 2028-2029, insurers get funder identity for free and a paid inference product is worth little. Second, the data-linkage claim is weaker than stated: consumer pre-settlement advances to individual plaintiffs are generally not UCC-1 filed (UCC-1s attach to businesses and law-firm portfolio deals), so the 'cross-join UCC-1 to open claims' mechanic likely resolves only firm-level portfolio funding, not per-claim funding at FNOL. Georgia's registry lists funders and their owners, not which cases they funded — the case linkage is the hard, unsolved part and the 90-day plan quietly assumes it. Third, Verisk or Findevor can bolt this on as a feature the moment it looks valuable; neither lacks the docket data or the carrier relationships. | O7: [lens] Litigation-propensity and attorney-involvement scoring at FNOL for casualty claims is an established, funded product category (CLARA Analytics, Charlee.ai, LexisNexis Risk attorney-representation data, Verisk claims analytics), and 'was this claim funded' is an additional attribute inside a model those incumbents already sell to exactly this buyer. Meanwhile every data primitive named as the moat — NMLS bulk registration data, UCC-1 filings, docket data, shell-layer beneficial-ownership resolution — is already a commodity from established vendors. [lens] The trigger is real but it does not produce the product. The registries create a list of FUNDERS and their beneficial owners; they do not create a claim-level linkage, and the entire value proposition is 'flag probable funder involvement at first notice of loss.' The bridge from a funder registry to a specific open claim is the proposed UCC-1 / docket / plaintiff-firm-graph inference, and that bridge is weak where it matters most: consumer legal funding is structured as a non-recourse purchase of case proceeds from an individual plaintiff and is generally not perfected by UCC-1 against that plaintiff, so UCC-1 filings surface law-firm-level portfolio lending, not the per-claim consumer funding that drives casualty severity. At FNOL — before a complaint is even filed and therefore before any docket exists — the signal is thinnest of all, which is precisely the moment the product claims to fire. Second objection: this is not a vacuum. Attorney-involvement and litigation-propensity scoring at FNOL is a mature product category (CLARA Analytics, Charlee.ai, Verisk's claims analytics), and docket/firm-network analytics is owned by Lex Machina, Trellis and Bloomberg Law. 'Funded' is an incremental attribute bolted onto an occupied product slot, not a new one. Third: the Law.com FOIA is offered as 'the clearest proof nobody has productized this,' but NMLS registration records are substantially public via NMLS Consumer Access, so a reporter filing an open-records request for ownership detail evidences a modest gap, not a category-wide absence — and journalists routinely FOIA data that vendors hold but do not publish free.
A8: 7 | B8: Forward exchange for transformer and switchgear production slots | C8: Physical / industrial | D8: grid-equipment-slot-forward-exchange | E8: Search-backed | F8: 7 | G8: 7 | H8: 7 | I8: 7 | J8: 6 | K8: =ROUND(F8*Overview!$B$24+G8*Overview!$B$25+H8*Overview!$B$26+I8*Overview!$B$27+J8*Overview!$B$28,2) | L8: Clearinghouse for orphaned transformer, switchgear and turbine production slots: OEM-confirmed listings, standardized spec templates, escrow, assignment paperwork, and eventually a forward curve on MVA by delivery quarter. | M8: Highest composite in the entire pool (6.88) and I am overriding the both-refuted rule deliberately. Both skeptics self-reported confidence 6, both disclosed they ran ZERO live searches, and both explicitly conceded 'no venue trading forward slots exists — that absence is real.' Their kill is OEM anti-assignment clauses, which is a deal-structure objection rather than a market objection: assignment-with-consent is routine where the substitute buyer is creditworthy and the OEM's slot stays filled at no cost to it, and the business runs perfectly well as a consented-novation brokerage plus price discovery rather than as bearer-instrument trading. The underlying scarcity is not in dispute — 128-week LPT and 144-week GSU lead times are independently verified, capacity is allocated by prepayment, and FERC's 18 June 2026 §206 show-cause orders to all six RTOs (responses due 17 Aug 2026) are confirmed across six law-firm sources. Ranked 7 not 1 because if OEMs systematically refuse consent to capture the spread themselves there is no business at all, engineered-to-order units are less fungible than the spec template assumes, and six of ten evidence URLs are X posts. This is the highest-variance name on the list. | N8: The whole business runs through the OEM's consent. Standard supply agreements carry anti-assignment/anti-delegation clauses and non-refundable staged deposits; once an OEM learns a slot is worth more than the contract price it has every incentive to cancel, keep the deposit and re-sell at market itself rather than let a broker capture the spread. Warranty assignability is separately restricted. Second risk: the phantom-demand premise is contested — SemiAnalysis published 'Stop Saying Half of 2026 US Datacenter Capacity Is Canceled' rebutting exactly the cancellation statistic this thesis rests on, and if hyperscaler demand holds, orphaned slots never accumulate and there is nothing to clear. Third: Anza already runs a new-equipment exchange plus a procurement desk and is one product decision away from listing undelivered slots. Evidence quality is also weak — six of the ten cited URLs are x.com posts. | O8: [lens] The option value in a cancelled slot accrues to the OEM, not to the depositor, so there is nothing for a clearinghouse to clear. Orders with GE Vernova, Hitachi Energy, Siemens Energy, Eaton, Schneider and ABB carry anti-assignment terms requiring manufacturer consent, and in a sold-out market the OEM's dominant strategy is to refuse consent, keep the 10-30% deposit, and resell the slot itself at the new higher price — the OEM order desk the candidate wants to verify listings with is the incumbent that absorbs this. Compounding it, these units are engineered-to-order: the candidate's own standardization fields (kVA, voltage class, impedance, delivery window) understate BIL, tap changers, bushings, cooling class, footprint and test standards, which is precisely why a slot built for one site is often useless to another. And the adjacent brokerage layer that could add forward slots tomorrow is already capitalized — Maddox Industrial Transformer, Solomon Corporation, T&R Electric, Transformer Exchange — while build.inc, cited in the candidate's own evidence, already sells datacenter transformer procurement intelligence. [lens] The shortage is real but the tradable instrument probably is not. A transformer/GSU 'slot' is not a bearer option — OEM purchase orders (GE Vernova, Hitachi Energy, Siemens Energy, Eaton, Schneider, Prolec, Virginia Transformer) carry anti-assignment clauses and cancellation/liquidated-damages schedules, so the slot cannot change hands without OEM consent, and the OEM has every incentive to withhold consent, keep the non-refundable deposit, and resell the slot itself at the current (much higher) price. The OEM order desk is the natural clearinghouse and already captures the entire arbitrage. Second, large power transformers are engineered-to-order (impedance, BIL, bushing arrangement, footprint, noise, seismic); a partially-engineered unit is not fungible across buyers, so the 'standardize on kVA/voltage/impedance' template collapses for exactly the units that are scarcest. Third, the cited FERC trigger is decorative: a co-location/large-load interconnection-study rulemaking changes queue processing, not equipment-contract assignability. Fourth, the double-booking that supposedly creates orphan supply argues the opposite way — holders keep duplicate slots deliberately as insurance and release them only at the point of cancellation, when the OEM keeps the deposit. Fifth, the party with budget (hyperscalers, big utilities) buys via multi-year frame agreements and reserved-capacity prepayments direct with OEMs and has no need of a 2-4% broker; the desperate marginal developer is the one without money.
A9: 8 | B9: Key-state custody for LMS/XMSS firmware signing under CNSA 2.0 | C9: Infrastructure & standards | D9: stateful-hash-signature-key-state-custody | E9: Recall-only | F9: 6 | G9: 5 | H9: 7 | I9: 4 | J9: 6 | K9: =ROUND(F9*Overview!$B$24+G9*Overview!$B$25+H9*Overview!$B$26+I9*Overview!$B$27+J9*Overview!$B$28,2) | L9: Signing API in front of cloud HSMs that allocates monotonic one-time-key indices under a replicated ledger, reserves disjoint HSS/XMSS-MT subtrees per builder so parallel CI can never collide, refuses to sign on ambiguous state, and emits tamper-evident index-usage audit evidence. | M9: The ONLY candidate in round 1 whose overlooked claim survived live verification: 'XMSS LMS hash-based signature' returns exactly three repositories worldwide, all academic or archived, and every one of seven code-search hits for SP 800-208 is a crypto-inventory scanner classifying the algorithm in a lookup table. Nobody ships state management. The distinctive real insight is that CNSA 2.0 mandates stateful LMS/XMSS rather than ML-DSA for firmware signing, which converts code signing into a crash-consistent distributed-state problem where one HSM clone, DR failover or CI rerun permanently destroys a device root of trust — genuinely nasty, genuinely unowned, and exactly the kind of narrow correctness problem two strong engineers can own. Held to 8 by a binary regulatory risk the screener named precisely: NSA has signalled it anticipates permitting stateless ML-DSA for firmware signing in future guidance, and if that lands the entire reason for the company evaporates with no adjacent market to absorb the pivot. The '1 Jan 2027 gate' is a vendor-blog gloss on NSA's timeline, and the dossier's sources contradict each other on the EO number. | N9: NSA has signaled it anticipates permitting stateless ML-DSA for firmware signing in future CNSA 2.0 guidance; if that lands, the catastrophic-state-management problem the entire company exists to solve simply stops being mandatory, and the narrow NSS/DIB buyer base means there is no adjacent market large enough to absorb the pivot. | O9: Not selected for verification
A10: 9 | B10: Copper sunset triage for fire-alarm, elevator and area-of-refuge lines | C10: Physical / industrial | D10: copper-retirement-life-safety-circuits | E10: Recall-only | F10: 6 | G10: 6 | H10: 5 | I10: 5 | J10: 5 | K10: =ROUND(F10*Overview!$B$24+G10*Overview!$B$25+H10*Overview!$B$26+I10*Overview!$B$27+J10*Overview!$B$28,2) | L10: National data layer joining carrier copper-retirement and §214 discontinuance filings to commercial property, elevator permit and fire-inspection records, sold as a per-line compliance registry with sequenced cutover runbooks and inspector-ready documentation. | M10: The most plausible overlooked claim in round 1 at the layer proposed: the hardware and integrator lanes are unambiguously crowded (Ooma AirDial, NAPCO, Telguard, Kings III, Pye-Barker), but the normalized wire-center-to-building blast-radius dataset has no owner, hardware vendors have no incentive to build it and integrators cannot. The trigger is dated and the code obligation is genuinely non-discretionary: the FCC voted 26 March 2026 to streamline retirement, declined to impose any compatibility requirement on replacements, and cut notice from 180 to 90 days — which is not enough time for a facilities manager to inventory, source, install, test and re-inspect NFPA 72 and ASME A17.1 circuits. Held to 9 by a specific technical kill that may be fatal: FCC filings identify wire centers and CLLIs, not addresses, and after number portability you cannot reliably map a phone number to a serving wire center without licensed LERG/porting data, so the free 'is my building in the blast radius' checker that drives the whole funnel may not be deliverable at the promised fidelity. Test that join in week one. | N10: The core data join may not be buildable as described — FCC filings identify wire centers/CLLIs, not addresses, and after number portability you cannot reliably map a phone number to a serving wire center without licensed LERG/porting data, so the free 'is my building in the blast radius' checker that drives the whole funnel likely cannot be delivered at the promised fidelity. | O10: Not selected for verification
A11: 10 | B11: CUI determination and marking for small defense machine shops | C11: Regulatory clock | D11: cui-determination-for-machine-shops | E11: Search-backed | F11: 6 | G11: 7 | H11: 7 | I11: 5 | J11: 4 | K11: =ROUND(F11*Overview!$B$24+G11*Overview!$B$25+H11*Overview!$B$26+I11*Overview!$B$27+J11*Overview!$B$28,2) | L11: Engine that ingests customer drawings and PDFs, reads DoD distribution statements and DFARS flow-down clauses, decides CUI vs FCI vs neither, applies markings, and emits shop-floor labels plus a defensible audit trail — sold through CMMC consultancies at scoping. | M11: Both skeptics refuted this, and I am retaining it with a rebuttal. Neither ran a live search; both attacked demand and legality rather than the screener's live-verified finding that four differently-worded searches surfaced no product doing this. Their strongest objection — CUI designation is a government function under 32 CFR 2002 and DoDI 5200.48 — is legally true and practically beside the point: unmarked flow-down is precisely the documented pain, which is why Totem publishes a CUI Identification Guide aimed at exactly this buyer and why consultancies bill scoping workshops as a named SKU. Their fallback, 'just treat everything as CUI,' is not free — it drags the entire shop into the GCC High enclave, and enclave seat cost is the very expense scoping reduces. The trigger is the cleanest in round 2 and has not slipped: 48 CFR CMMC published 10 Sep 2025, effective 10 Nov 2025, Phase 2 third-party Level 2 ramp from ~Nov 2026 across tens of thousands of small shops. Ranked 10 because the real risk is channel conflict — you are asking consultancies to resell a tool that deletes their most-billed hour — plus Purview auto-labeling already sitting paid-for in every GCC High tenant. | N11: why_now verified and holds: 48 CFR CMMC final rule published in the Federal Register 10 Sep 2025, Phase 1 effective 10 Nov 2025, DFARS 252.204-7021 now in new solicitations, Phase 2 third-party Level 2 ramp from ~Nov 2026. Real risks are commercial, not factual. (1) Channel conflict: CUI scoping is the most-billed hour in a consultancy's engagement — a tool that automates it cannibalizes the reseller's own revenue, so 'they will resell it' is the weakest link in the thesis. (2) Liability: a shop will not accept an automated CUI determination without a human attestation, so the product degrades into a workpaper generator with consultant sign-off, compressing price. (3) One-time purchase shape — scoping happens at engagement start, not monthly, so recurring revenue is unproven. (4) Microsoft Purview is already paid-for in every GCC High seat and is the path of least resistance for the MSP channel. (5) Small ACV against a long tail of 30-person shops facing $20k-$100k total compliance cost, most of which goes to the enclave, not to determination. | O11: [lens] Data classification and auto-labeling is one of the most crowded categories in enterprise security, and the CUI-specific slice is explicitly productized: Microsoft Purview sensitivity labels plus trainable classifiers ship inside the GCC High tenant that every CMMC enclave vendor already deploys, so the incumbent does not need to 'add this next quarter' — it is bundled in the thing the shop is already buying. Dedicated CUI marking products exist (Fortra's Titus and Boldon James, Janusnet/janusSEAL, all long-standing defense-marking tools), as does CUI discovery marketing from Varonis, Concentric AI and BigID. On the compliance side, CUI scoping and data-flow mapping is a standard billed line item in every CMMC readiness engagement and appears in the CMMC platforms themselves (FutureFeed, Totem Technologies, Kiteworks, PreVeil, Summit 7, Steel Root, Cuick Trac, Exostar, Ignyte). 'Parse distribution statements out of PDF and CAD title blocks' is a feature, not a company. [lens] The trigger is genuinely solid — this is the one date in the batch I can independently confirm — but the product sits on the wrong side of a legal boundary and loses to a free workaround. Under 32 CFR Part 2002 and DoDI 5200.48, CUI designation is a GOVERNMENT function: the requiring activity/contracting officer identifies and marks CUI in the contract; a contractor is not an authorized designating official. A tool that 'decides CUI vs FCI vs neither' therefore sells an unauthorized determination that increases the shop's and the reselling consultant's liability rather than reducing it. In practice the dominant strategy — free, instant and defensible at assessment — is 'treat everything a DoD prime sends us as CUI and keep it in the enclave,' which is exactly what the enclave vendors already sell and which makes per-document classification moot. Where classification is genuinely wanted, it is already bundled: Microsoft Purview sensitivity labels, auto-labeling and trainable classifiers ship inside the GCC High E5 licensing these shops are already forced to buy, and Fortra/Titus, Janusnet, PreVeil and Kiteworks all address CUI handling. The channel is also misaligned: the record's own pitch is that this automates 'the most-billed and least-automated hour' in a consultancy's scoping engagement — consultancies bill hours, so you are asking them to resell a product that deletes their revenue. And the buyer is the most price-resistant in the defense base: a 30-person shop already facing $20-100k of CMMC cost, with a well-documented pattern of small shops exiting the DoD supply chain instead of paying.
A12: 11 | B12: State packaging EPR reporting for mid-market brands | C12: Regulatory clock | D12: rec-state-packaging-epr-reporting-for-mid-market-brands | E12: Thin | F12: 5 | G12: 7 | H12: 8 | I12: 5 | J12: 6 | K12: =ROUND(F12*Overview!$B$24+G12*Overview!$B$25+H12*Overview!$B$26+I12*Overview!$B$27+J12*Overview!$B$28,2) | L12: Physically weigh and characterize every SKU's packaging for a 50-500 SKU food or consumer brand, build the per-SKU material bill of materials, and file the differently-shaped producer report into each state's PRO on its own statutory calendar. | M12: Both skeptics refuted, and again I am retaining with a rebuttal, because both refutations were explicit recall-only with no live search and neither named a company whose ICP is the 50-500 SKU brand doing physical package characterization as a service. Lorax EPI and Ecoveritas are enterprise/EU compliance houses; Specright sells packaging spec management, not state EPR filings; Circular Action Alliance's portal is a submission surface, not the data assembly that feeds it. What survives is the strongest structural feature in the batch: a stacking multi-state calendar (Oregon live 1 Jul 2025, Colorado in fee assessment, Minnesota and Maryland phasing through 2026-2028, Washington enacted 2025) against the same underlying SKU dataset, producing genuine multi-state switching cost and a proprietary physical asset. Ranked 11 rather than higher because California SB 54's 2025 regulatory restart is real and delays the largest single market — proving these deadlines are politically soft — because de minimis exemptions carve out much of the long tail, and because weigh-and-characterize is real opex that caps gross margin. Re-run crowding on Specright, Lorax EPI and Reclay with live search before committing capital. | N12: The why_now largely holds: Oregon's Recycling Modernization Act program went live July 1 2025 with producer reporting, Colorado's program moved to fee assessment in 2025-2026, Minnesota (2024 law) and Maryland (2025) are phasing registration and reporting through 2026-2028, and Washington enacted its EPR law in 2025 — with Circular Action Alliance as PRO across the set, so the 'same SKU data, differently shaped report per state' wedge is real. The notable wobble is California: CalRecycle's SB 54 regulations were withdrawn and restarted in 2025 at the Governor's direction, delaying the largest single market — so a plan that leads with California revenue is mistimed, and further state-level delay or fee-structure softening under industry lobbying is the main risk. Secondary risks: PRO-provided portals plus co-packer-supplied spec sheets could commoditize the filing layer; the physical weigh-and-characterize step is real moat but is also real opex that caps gross margin and slows onboarding; and a $10-25k first-year price into a brand that has never had a packaging engineer is a hard first sale. Advancing on the strength of a verified stacking regulatory calendar, a proprietary dataset that demonstrably does not exist elsewhere, genuine multi-state switching cost, and a 90-day shippable manual wedge — conditional on re-running crowding checks on Specright, Lorax EPI and Reclay StewardEdge with live search. | O12: [lens] Packaging EPR reporting is a mature, 25-year-old European service industry whose vendors have been actively porting to US state programs since the CA/OR/CO/MN/MD laws passed — Ecoveritas and Valpak (both Reconomy), Lorax EPI (whose entire product is multi-jurisdiction packaging EPR data management and fee calculation), Reclay, and Trayak (EcoImpact-COMPASS, packaging LCA plus eco-modulated fee modeling aimed at exactly mid-market CPG). The candidate's claimed moat — 'per-SKU packaging bill-of-materials data doesn't exist anywhere' — is the product definition of Specright, a well-funded packaging specification data platform selling to food and CPG brands, and is also held by every co-packer and packaging converter in spec sheets. The PRO itself (Circular Action Alliance) supplies the reporting portal, templates and calendar across the covered states, which flattens much of the 'differently-shaped report per state' complexity the wedge depends on. [lens] Thinnest evidence base of the six and a wrong core premise. The record is self-labelled '[UNVERIFIED — no live web access this session]', its why_now contains no date at all and instead instructs the reader to 'verify current deadlines per state and Circular Action Alliance's reporting calendar,' and its entire evidence base is three organization homepages (calrecycle.ca.gov, oregon.gov/deq, circularaction.org) with zero captured quotes. Under a demand-and-trigger lens that is an unverified assertion, not a trigger. Substantively: (1) the flagship deadline has slipped — Newsom rejected CalRecycle's SB 54 regulations in March 2025 and ordered the rulemaking restarted, pushing California obligations right and proving this category's deadlines are politically soft; (2) the 'moat' premise is false — brands do not need to weigh their own cartons, because packaging converters and co-packers (WestRock, Amcor, Berry, Sealed Air, Graphic Packaging) supply unit weights and material composition on the spec sheet that accompanies every PO, and Specright already sells packaging-spec/BOM as a system of record to exactly this customer; (3) the field is crowded, not empty — Lorax EPI, Ecoveritas, Reverse Logistics Group, Trayak (EcoImpact-COMPASS, which added EPR fee modelling), Source Intelligence/Assent and consultancies (RRS, Eunomia, Anthesis, ERM) all sell packaging-EPR data assembly and filing, and Circular Action Alliance itself supplies the reporting portal, material category taxonomy and templates as part of the fee — a free substitute bundled with the obligation; (4) de minimis exemptions (roughly <$5M revenue in OR/CO, <$1M CA, plus tonnage floors) carve out much of the long tail the thesis counts on; (5) the eco-modulated fee itself is the dominant cost, so brands optimize spend toward fee reduction, not toward a $10-25k data-assembly engagement.
A13: 12 | B13: Part 146 ADSP certification: strategic deconfliction plus the sub-400-foot obstacle layer | C13: Infrastructure & standards | D13: part-146-bvlos-data-services | E13: Recall-only | F13: 5 | G13: 7 | H13: 5 | I13: 6 | J13: 7 | K13: =ROUND(F13*Overview!$B$24+G13*Overview!$B$25+H13*Overview!$B$26+I13*Overview!$B$27+J13*Overview!$B$28,2) | L13: Become a certificated Automated Data Service Provider in the near-empty supplemental-data lane by building the survey-grade, continuously refreshed national database of sub-400-foot obstacles — distribution lines, guy wires, met towers, cranes — that existing FAA obstacle data does not resolve. | M13: A federally certificated toll position on US low-altitude airspace with no established winner is a rare structural prize, and the strategic read is correct: visible entrants are all racing at deconfliction because it is the glamorous algorithmic part, leaving supplemental data thinner. The regulatory creation of the category is verified — the FAA BVLOS NPRM published Aug 2025 with proposed Part 146 following the June 2025 executive order, and the final rule reached OIRA 10 July 2026. Ranked 12 because the timing risk is severe and structural: BVLOS has slipped for a decade, the candidate's own revenue curve is 2028-2031 which sits entirely beyond a seed runway, and you would burn three years selling obstacle data into utility inspection budgets against Neara (~$45M) and AiDash (~$58M), who already exploit utility LiDAR and already sit inside those accounts. Second risk: the final rule may permit deconfliction ADSPs to self-supply data, collapsing the separate SDS market the whole thesis needs. | N13: Timing. BVLOS has slipped for a decade and the revenue curve the candidate itself puts at 2028-2031 sits entirely beyond a seed runway; if the final rule lands in 2027 and certification takes 18 months, you burn three years selling obstacle data into utility inspection budgets against Neara and AiDash, who are better capitalized and already inside those accounts. Secondary risk: the final rule may let deconfliction ADSPs self-supply data, collapsing the separate SDS market the whole thesis depends on. | O13: Not selected for verification
... A26: 25 | B26: Killing lead-line 'unknowns' before the Nov 1, 2027 LCRI baseline locks in | C26: Regulatory clock | D26: lead-service-line-inventory-2027 | E26: Recall-only | F26: 2 | G26: 6 | H26: 6 | I26: 5 | J26: 3 | K26: =ROUND(F26*Overview!$B$24+G26*Overview!$B$25+H26*Overview!$B$26+I26*Overview!$B$27+J26*Overview!$B$28,2) | L26: Drive the 'unknown' count toward zero before the LCRI baseline inventory locks on 1 November 2027, since unknowns are treated as lead and the baseline fixes each system's mandatory replacement rate for years. | M26: Included at 25 on the strength of one genuinely sharp mechanical insight: unknowns are deemed lead, and the 1 Nov 2027 baseline locks in a mandatory replacement rate, so every unknown resolved before that date removes capital obligation permanently — a rare case where diagnostic work has a directly computable dollar value to the buyer. Ranked last because the monetization design fails on public-procurement mechanics the screener identified correctly: municipalities cannot pay a contingency fee out of capital they merely avoided spending, so the outcome-priced model is largely uncontractable and the business collapses back into hourly engineering already performed by incumbent firms, with 120Water, BlueConduit and Trinnex holding the software layer and free federally-funded technical assistance anchoring price. The LCRI compliance date also sat under active litigation and EPA reconsideration, so even the date is not firm. | N26: The outcome-priced 'share of avoided replacement obligation' model is largely uncontractable in public procurement — municipalities cannot pay a contingency fee out of capital they merely avoided spending — so the business collapses back into hourly engineering work already done by incumbent firms. | O26: Not selected for verification

Sheet All Opportunities
A1: ID | B1: Opportunity | C1: In top 25? | D1: Rank | E1: Evidence | F1: Composite | G1: Verdict | H1: Thesis | I1: Why now | J1: Why overlooked | K1: The 90-day wedge | L1: Discovery lens | M1: Sources
A2: datacenter-as-grid-entity-compliance | B2: Ride-through models and curtailment proof for NERC-registered data centers | C2: Yes | D2: 1 | E2: Recall-only | F2: =IFERROR(INDEX('Screening Scores'!$I:$I,MATCH($A2,'Screening Scores'!$A:$A,0)),"") | G2: advance | H2: Data centers are becoming NERC-registered reliability entities with generator-like performance obligations, and almost nobody can do the engineering or produce the evidence. The business is a boutique that builds the filed dynamic model (EPRI UDM for the power-electronic portion, CMLD for cooling), runs disturbance-response testing of UPS transfer thresholds, rectifier and chiller settings, designs remediation, and assembles the attestation package — repeated per campus, per interconnection, per ISO, at roughly $150k-$600k a campus with mandatory re-validation after every trip event. Bolted onto that is the flexibility half: ERCOT's Provisional Controllable Load Resource construct splits a load into a firm portion and a SCED-dispatched flexible portion, and nobody sells the registration filings, penalty-exposure tracking, or the signed, timestamped metering record that proves each curtailment instruction was actually honored. Buyers are large-load customers (data center developers, electrolyzers, crypto) and the utilities that must administer these agreements; whoever owns the measurement and verification record owns the settlement. | I2: Four dated triggers have already fired. NERC issued a Level 3 Essential Actions Alert on 4 May 2026 — only the third in its 58-year history — with entity responses due 3 August 2026. FERC issued an order in Docket RD26-7-000 on 16 July 2026 directing NERC to file mandatory reliability standards for computational loads by 31 December 2026 and a Phase II work plan by 1 March 2027. FERC issued tailored Section 206 orders to every RTO on 18 June 2026 (Docket RM26-4) to accelerate large-load interconnection. ERCOT's NOGRR 282 grandfathers only facilities energized or study-complete on or before 14 November 2025 and imposes a 90-day root-cause / 90-day corrective-plan / 180-day implementation cycle after any failed ride-through. ERCOT is tracking more than 438 GW of large-load requests with roughly 198 GW applying in Q1 2026 alone, nearly 90% data centers — every one of which will need a filed, defensible model and a performance record by 2029-2031. | J2: The entire 'data center power' startup wave aimed at generation, siting and physical flexing (Emerald AI, VoltaGrid, Verrus, Build.inc), and the adjacent software money went to generator interconnection queue automation (Google/Tapestry HyperQ with PJM, Enverus SUGAR with MISO). Neither touches the load-side reliability-compliance obligation or the paperwork-and-proof layer that decides whether a curtailable interconnection agreement is granted, honored and paid for. Today that work sits with a handful of tiny consultancies (EPE Consulting, Keentel Engineering) and hyperscaler internal EE teams that have never filed a NERC-facing dynamic model; large-load interconnection is so new as a formal construct that incumbent transmission-planning software does not model it and consulting engineers do it by hand. NERC's own Large Loads Task Force white papers (Jul 2025, Mar 2026) describe this as a gap in existing practices and Reliability Standards. | K2: Two power-systems engineers with PSS/E and PSCAD licenses and EPRI UDM familiarity, starting in ERCOT where the construct is furthest along. 90 days: publish a free 'NOGRR 282 / NERC Level 3 Alert readiness gap assessment' aimed specifically at ERCOT large loads that are NOT grandfathered (energized after 14 November 2025), then convert to the paid dynamic model build plus UPS transfer-threshold study — field data collects off existing PQ meters at the point of interconnection, and the scarce input is the person who can translate IEC 62040-3 UPS transfer behavior into an ISO-acceptable load model. Second product, sold to the same three data center developers already paying consultancies per filing: the PCLR/Batch Zero registration and modeling data pack (PGRR145 artifacts, ride-through documentation, self-limiting control descriptions) as guided software, plus a metering pipeline that emits a signed, timestamped curtailment performance record against each dispatch instruction. | L2: Physical world — industry, energy, grid, water, logistics, materials, construction; Revealed enterprise demand — what large organizations are actively trying to buy or staff for | M2: https://www.powermag.com/ferc-orders-mandatory-nerc-reliability-standards-for-data-center-and-other-computational-loads/ https://www.nerc.com/newsroom/ferc-sets-year-end-deadline-for-nerc-to-finalize-registry-criteria-and-standards-for-computational-loads https://www.rtoinsider.com/136792-ferc-directs-large-loads-standards-by-end-of-2026/ https://www.ercot.com/files/docs/2026/03/02/04_LEL-RT-Requirements_SPWG_Feb2026.pdf https://epeconsulting.com/epe-intelligence/news/preparing-for-nogrr-282-ercot-s-next-phase-of-large-load-requirements https://www.utilitydive.com/news/data-center-load-disruptions-nerc-alert-recommendations/818036/ https://www.latitudemedia.com/news/as-more-data-center-trip-off-the-grid-ride-through-rules-gain-steam/ https://www.nerc.com/globalassets/who-we-are/standing-committees/rstc/whitepaper-characteristics-and-risks-of-emerging-large-loads.pdf https://www.utilitydive.com/news/texas-facing-438-gw-queue-approves-initial-large-load-interconnection-pro/823367/ https://www.ferc.gov/rm26-4 https://www.ercot.com/services/rq/large-load-integration https://www.zeroemissiongrid.com/insights-press-zeg-blog/ercot-large-load-interconnection-2026/
A3: long-tail-customs-entry-and-duty-recovery | B3: Entry Type 13 and instrument-aware duty recovery for the post-de-minimis long tail | C3: Yes | D3: 2 | E3: Recall-only | F3: =IFERROR(INDEX('Screening Scores'!$I:$I,MATCH($A3,'Screening Scores'!$A:$A,0)),"") | G3: advance | H3: The $800 de minimis exemption is gone, so parcels that used to clear on a manifest now need a real entry with 10-digit HTS classification, valuation, origin, an EIN and a bond — filed by licensed customs brokers, a profession gated by an exam with a 12-22% pass rate. That is a hard supply constraint meeting a demand shock. Build software that lets one licensed broker supervise 50-100x the entry throughput on low-value shipments, sold as entry-as-a-service to the SMB importers who have never spoken to a broker and for whom $50-100 of brokerage on a $500 shipment destroys unit economics. Bolt on the second half: duty recovery eligibility now varies sharply by which legal instrument a tariff was imposed under (Section 301 duties are generally drawback-eligible, Section 232 generally not), and reasoning across instrument, HTS line, country of origin and disposition is exactly the legal-grade work that LLMs newly do at near-zero marginal cost. The license is the moat; software multiplies it. | I3: De minimis ended for China/Hong Kong on 2 May 2025 and for all countries on 29 August 2025; the One Big Beautiful Bill Act signed 4 July 2025 permanently repeals the statutory basis effective 1 July 2027; and on 24 June 2026 CBP published an indefinite suspension of the administrative exemption. FY2024 saw over 1.36 billion de minimis packages enter the US. The integration door opens in seven weeks: CBP begins a voluntary ACE test of Entry Type 13 — a fully electronic informal-entry path for shipments valued at $2,500 or less — on 22 September 2026. On the recovery side, search-level sources report that following a February 2026 Supreme Court ruling (6-3) that IEEPA does not authorize tariffs, CBP launched the CAPE refund system on 20 April 2026, with roughly 75,300 CAPE declarations covering over 11.2 million entries submitted by 26 April — six days of filings covering eleven million entries. VERIFY BEFORE ACTING: the scout could not page-verify the SCOTUS holding or the CAPE figures; treat them as strong search extracts, not diligence. The strategic read is unchanged either way — striking IEEPA channels protectionism into Section 232/301/122 instruments with different eligibility and refund mechanics, creating a permanent reclassification and recovery surface. | J3: The visible startups — Zonos, Passport, Portless, Flexport — sell cross-border to consumer brands with real volume and real ops teams. The stranded population is the small domestic importer: the Etsy-scale seller, the parts distributor, the specialty retailer bringing in a pallet, whom 3PLs and forwarders are actively turning away. Nobody has attacked the broker-capacity bottleneck itself, which is the actual scarce asset, because investors read 'customs brokerage' as a low-margin services business. On recovery, roughly 80% of eligible refunds are never filed and about $15 billion in eligible tariff refunds go unclaimed annually — true for years because matching import entry lines to export lines cost more than it recovered below Fortune-500 scale; Charter Brokerage alone accounts for approximately one-third of all US duty drawback refunds, on 50/50 contingency splits and 9-12 month timelines. Honest caveat: 'best duty drawback companies in 2026' listicles now exist, so plain drawback-as-a-service is no longer uncontested — the unwritten layer is instrument-aware planning (drawback vs. FTZ vs. bonded warehouse vs. first-sale valuation vs. tariff engineering, per SKU per instrument), which today is sold as $800/hour trade-attorney time. | K3: 90 days, two people plus one licensed customs broker as co-founder, advisor or broker-of-record — the license is a hiring problem, not a technical one. Product one: an HTS classification assistant plus an ACE ABI filing pipeline aimed at Entry Type 13, joining CBP's 22 September 2026 voluntary test as a day-one participant, delivered as a Shopify/WooCommerce/marketplace app that classifies a merchant's SKU catalog once, stores rulings and origin evidence, and auto-files at a flat per-entry price well under the incumbent $50-100. Product two, sold to the same accounts: ingest ACE entry summary data (importers can grant agent portal access today) plus export/destruction records and ship an eligibility triage that says, per entry line, which instrument applied, whether it is drawback-eligible, and the dollars at stake — priced flat, which is the obvious wedge against 50/50 contingency incumbents. Distribution: 3PLs and freight forwarders currently declining small accounts. | L3: Reddit / unglamorous-trades practitioner lens; The startup graveyard — ideas that died for a reason that no longer applies | M3: https://www.federalregister.gov/documents/2026/06/24/2026-12670/indefinite-suspension-of-the-de-minimis-exemption-for-merchandise-arriving-through-all-modes-other https://www.whitecase.com/insight-alert/united-states-suspend-customs-de-minimis-entry-most-shipments-august-29-2025 https://www.bdo.com/insights/tax/cbp-suspends-de-minimis-exemption-and-introduces-new-postal-entry-requirements https://gingercontrol.com/blog/de-minimis-repeal-small-importer-impact https://www.cbp.gov/trade/programs-administration/customs-brokers/license-examination-notice-examination https://customsbrokerindex.com/blog/customs-broker-exam-how-to-pass/ https://albawheelsup.com/trade_news/cbp-makes-it-official-de-minimis-is-gone-for-good-and-a-new-postal-entry-process-is-on-the-way/ https://lightsource.ai/blog/duty-drawback-practical-guide-recovering-import-duties-2026 https://passportglobal.com/blog/recover-import-tariffs-duty-drawback-ecommerce/ https://www.ajot.com/news/best-duty-drawback-companies-in-2026-compared-by-speed-cost-recovery https://www.zollback.com/blog/section-duty-drawback https://www.customsmanager.info/post/us-tariffs-duty-drawback
A4: nuclear-naval-supplier-qualification | B4: NQA-1 qualification and commercial grade dedication as a service | C4: Yes | D4: 3 | E4: Recall-only | F4: =IFERROR(INDEX('Screening Scores'!$I:$I,MATCH($A4,'Screening Scores'!$A:$A,0)),"") | G4: advance | H4: The binding constraint on both the US nuclear build-out and the submarine industrial base is qualification, not capital, fuel or reactor design: a competent machine shop, forge, valve maker or cable house cannot sell a safety-related part until its quality program is audited against 10 CFR 50 Appendix B / ASME NQA-1 or NAVSEA requirements, and a commercial off-the-shelf part cannot be used until an engineer performs commercial grade dedication identifying and verifying critical characteristics. Today that is bespoke consulting in Word documents, and the only reuse mechanism (NUPIC) is a closed utility club new entrants structurally cannot join. Build the industrialised path: a fixed-fee turnkey program that installs an Appendix B / NQA-1 quality system in an existing AS9100 or ISO 9001 shop, plus — the real product — an outsourced dedicating-entity service with a structured critical-characteristics library, guided Method 1-4 verification workflow, and exportable, auditable dedication packages. Revenue is per-supplier onboarding plus recurring per-lot dedication fees and re-audit retainers. | I4: The Nuclear Scaling Initiative's landscape report, covered by ANS on 23 March 2026, names the qualification pathway itself as the bottleneck — 'strict quality standards, including NQA-1, narrow the supplier base and slow expansion,' and without 'more efficient, repeatable approval pathways' the domestic industrial base cannot grow — alongside shortfalls in nuclear-qualified machinists, welders, inspectors and NDE specialists. Demand finally broke the chicken-and-egg deadlock in 2025-2026 via hyperscaler nuclear PPAs, plant restarts, the ADVANCE Act, DOE reactor pilot programs and a federal 300 GW-by-2050 target. On the naval side the money is already obligated: a roughly $950M NAVSEA award to BlueForge Alliance and 169 supplier projects totaling $648M across 32 states, against a submarine supplier base that has contracted from 17,000 to about 5,000 since the Cold War. Qualification takes 12-36 months, so shops that start in 2026 are the ones with capacity when first-of-a-kind SMR fabrication and fleet orders land in 2028-2031 — every month of delay now is a schedule slip then. | J4: Nuclear venture capital went almost entirely to reactor developers, fuel (HALEU) and now data-center PPAs. The qualification layer is served by aging QA consultancies billing hourly with no leverage, by ASME certification (a credential, not a service), and by incumbents like Curtiss-Wright and Paragon whose model is selling their own dedicated parts rather than enabling other people's suppliers. The problem is described in the trade literature as 'workforce qualification,' which reads as a training problem and gets answered with curricula rather than software. The reuse infrastructure entrenches the gap: NUPIC eligibility requires sponsorship by five member licensees and enrolls you into a 33-month audit cycle designed for the operating LWR fleet, and NIAC is likewise an incumbent club. Searches for nuclear supplier qualification software return NRC pages, EPRI reports and consortium PDFs — no vendor. (Evidence caveat: two of the three scouts were blocked from opening pages and worked at search-extract level.) | K4: Two to three people: ideally one ex-NUPIC lead auditor, one ex-supplier quality manager, one technical writer. 90-day wedge, product one: a fixed-price 'Appendix B readiness sprint' sold to five non-nuclear precision shops in Tennessee, Ohio and the Carolinas that already hold AS9100 or ISO 9001 and are chasing SMR RFQs — deliver the QA manual, procedure set and a mock audit for roughly $75-150k per shop plus an ongoing audit retainer. Product two, higher margin and faster to cash: commercial grade dedication on named obsolete or long-lead items for operating plants, which wins on both cost and schedule against reverse engineering or plant modification. Do not try to replace NUPIC — build the CGD workbench (critical-characteristics library keyed to common component families, guided Method 1-4 workflow, exportable dedication package) and sell it to two advanced-reactor developers and their top ten suppliers, where identical parts are being dedicated repeatedly across buyers and the reuse value is immediately measurable. Referral channel: reactor developers and BlueForge-funded supplier expansion programs with a starved supply base. | L4: X / Twitter builder, operator and investor discourse (cross-validated against dated primary sources); Physical world — industry, energy, grid, water, logistics, materials, construction, defense-adjacent (search-level evidence only); Revealed enterprise demand — what large organizations are trying to buy or staff for (search-level evidence only) | M4: https://www.ans.org/news/2026-03-23/article-7870/nsi-report-addresses-supply-chain-bottlenecks/ https://www.nuclearscaling.org/publications/getting-ready-to-scale-addressing-u-s-nuclear-energy-supply-chain-constraints/ https://www.asme.org/certification-accreditation/nuclear-quality-assurance-nqa1-certification https://forgedops.com/glossary/procurement-supplier-qa https://www.smrfacility.com/smr-vendor-supplier-guide/ http://large.stanford.edu/courses/2026/ph241/garcia1/ https://www.nuclearscaling.org/wp-content/uploads/2026/03/2026-Landscape-of-U.S.-Domestic-Advanced-Nuclear-Energy-Supply-Chain.pdf https://www.nrc.gov/reactors/new-reactors/how-we-regulate/oversight/quality-assurance/nonconformances-violations https://www.power-eng.com/nuclear/a-better-way-to-address-aging-and-obsolescence/ https://efcog.org/wp-content/uploads/Wgs/Safety%20Working%20Group/_Quality%20Assurance%20Subgroup/Supply%20Chain%20Quality/Documents/Supplier%20Quality%20Management.pdf https://www.nrc.gov/reactors/new-reactors/how-we-regulate/oversight/quality-assurance/nupic-industry https://www.nrc.gov/reactors/new-reactors/how-we-regulate/oversight/quality-assurance/vendor-insp/comm-grade-dedication
A5: biosolids-outlet-exchange | B5: PFAS-Compliant Biosolids Outlet Exchange for the Mid-Atlantic | C5: Yes | D5: 4 | E5: Search-backed | F5: =IFERROR(INDEX('Screening Scores'!$I:$I,MATCH($A5,'Screening Scores'!$A:$A,0)),"") | G5: advance | H5: State by state, the cheapest disposal route for municipal sewage sludge — land application on farms — is being closed by PFAS limits, leaving wastewater utilities with hundreds of wet tons a day and no default legal destination. The business is a regional biosolids logistics and outlet brokerage: contract landfill airspace, thermal destruction slots and compliant out-of-state farmland, then match that capacity against each utility's tonnage and PFAS test results at a firm per-wet-ton price with compliance documentation attached. The second, stickier product is upstream industrial source control — finding and fixing the dischargers loading the plant so cheap outlets stay open. No capex; the margin is in knowing which outlet accepts which PFAS concentration under which state rule this quarter. | I5: The regulatory cascade is live and dated: Maine and Connecticut have enacted effective bans on land application; Maryland's SB 719, signed 28 April 2026, prohibits land application at or above 50 ppb PFOA/PFOS from 1 October 2028; six legislative efforts were enacted by May 2026 across Washington (two laws), Rhode Island, Oregon, Wisconsin and Connecticut; EPA published Draft Guidance for Reducing Risk from PFOA and PFOS in Biosolids on 1 July 2026, pushing systems toward industrial source identification; Pennsylvania has a tiered framework proposed and eight states already mandate WWTP PFAS monitoring. Each new state converts a free disposal route into a paid one and widens the arbitrage between basins, repricing the national biosolids stream from near-zero-cost byproduct to managed waste with a real gate fee by 2029-2031. | J5: PFAS venture attention is entirely on destruction technology (SCWO, plasma) and drinking-water treatment media. The boring middle — who trucks what, where, under which threshold, at what price — is handled ad hoc by haulers and by utilities' own operations staff. It is a matching and contracting problem whose legal constraint changes state by state and year by year, which is exactly the complexity that sustains an intermediary and repels a product company. | K5: Two operators with waste-logistics backgrounds, no capital equipment. In 90 days: target the Mid-Atlantic where Maryland's October 2028 clock and Pennsylvania's pending rule overlap, sign non-exclusive outlet capacity at three landfills and one incinerator, and sell 10 mid-size POTWs a firm per-wet-ton price with a compliance packet covering the receiving state's threshold. First customer is a mid-size municipal authority whose current land-application contractor has just told them 2028 is a problem; land them on a one-year firm-price agreement, then sell the source-control audit. | L5: Physical world — industry, energy, grid, water, logistics, materials, construction, defense-adjacent | M5: https://www.wastedive.com/news/state-action-pfas-contamination-sewage-sludge-oklahoma-maryland-mid-atlantic-biosolids/810713/ https://www.epa.gov/system/files/documents/2026-06/draft-guidance-reducing-risk-pfoa-pfos-biosolids.pdf https://www.bdlaw.com/publications/evolving-state-regulation-of-biosolids-recycling-in-the-pfas-era/ https://www.biocycle.net/pfas-biosolids-state-regulations-organics-recyclers/ https://www.valicor.com/blog/epas-new-pfas-biosolids-guidance-could-put-more-attention-on-industrial-wastewater https://floridaspecifier.com/may-june-2026/biosolids-policy/ https://www.rockinst.org/blog/emerging-state-regulations-of-pfas-for-biosolids/
A6: cra-embedded-sbom-and-cve-triage | B6: Reachability-grade SBOMs and kernel-CVE triage for embedded Linux | C6: Yes | D6: 5 | E6: Recall-only | F6: =IFERROR(INDEX('Screening Scores'!$I:$I,MATCH($A6,'Screening Scores'!$A:$A,0)),"") | G6: borderline | H6: The CRA's expensive, recurring engineering cost is not writing an SBOM — it is deciding, every week, whether this week's kernel and package CVEs actually reach a specific shipped device, and proving it in a document that survives a market surveillance authority. Build the embedded compliance auditor: ingest a Yocto/Buildroot/PetaLinux build (or a raw firmware binary), emit an SBOM that scores clean against BSI TR-03183-2 rather than merely being schema-valid, index reachability from the kernel .config, defconfig and driver set, and run that index daily against the kernel CNA feed. Output a ranked affects-you / does-not-affect-you list with OpenVEX statements carrying justification strings ('not exploitable: subsystem not compiled in'), candidate backport patches, and the declared-support-period and technical-documentation artifacts. Charge per device family per year — this is a maintenance annuity attached to hundreds of millions of shipped units. | I6: Reporting duties start 11 September 2026 and apply to products already on the market — so vendors owe answers before they own the inventory and reachability data needed to answer. Full application and CE marking land 11 December 2027, with Annex I Part II mandating an SBOM covering at least top-level dependencies, and the vertical product standards for routers, smart locks, cameras, microcontrollers and industrial firewalls were requested for delivery by 30 October 2026 — roughly a year of lead time. The kernel community now issues roughly fifty CVEs a week with no severity scores, while the default support window for a new LTS kernel has contracted from six years to two, widening the gap between what SoC vendors ship and what a CRA support period demands. And capacity is missing: on 11 June 2026 the CRA's notified-body rules began to apply with none designated, and accreditation typically takes 12-18 months. | J6: The CRA vendor landscape crowded into SBOM generation, storage and policy documentation and skipped both ends of the real work: the reachability decision, and whether the resulting document actually passes the de-facto quality benchmark. Maintainers document the gap themselves — a July 2026 CycloneDX .NET issue from a team preparing for CRA reports scoring 5.0 out of 10 on sbomqs because supplier, license, hash and dependency-depth fields simply are not in package metadata; relusion/CycloneDX.CRA.Validator, which checks against BSI TR-03183-2 v2.1.0, has 1 star, while cdxgen (generation) has ~1,023. The embedded estate where CRA's Annex III product classes actually live was skipped because it needs binary analysis and BitBake knowledge security vendors do not have: 'yocto SBOM' returns eleven repositories, the largest a 38-star vendor lead magnet, and the genuinely CRA-shaped tools are weeks old and tiny (shipcheck 17 stars created 2026-04-01, complira/yocto-sbom 3 stars, BitVex 1 star created 2026-05-29). BSP maintenance is served by boutique consultancies (Timesys, Koan, Ginzinger), not a scalable product; LTS-for-OSS exists for JavaScript and enterprise frameworks (HeroDevs) but not for embedded Linux. | K6: Two people with kernel experience, 90 days, one SoC family (NXP i.MX8 or TI AM62). Take a customer's Yocto/Buildroot manifest plus kernel .config, build the reachability index (is the vulnerable file compiled, is the subsystem enabled, is the interface exposed), run it daily against the kernel CNA and CVE feeds, and emit the ranked verdict list with justification strings plus OpenVEX. Free wedge with immediate pull: SBOM extraction from legacy firmware images that cannot be upgraded to a modern Yocto release, and a free BSI TR-03183-2 scoring report on whatever SBOM the customer already generates — then charge for the field enrichment, the signed attestation, and the per-device-family annual subscription. First customers: industrial and medical-adjacent device makers already fielding CRA questions from integrators. | L6: The dated regulatory and standards pipeline (2027-2031 compliance clocks); Developer, protocol, data, and standards-layer gaps | M6: https://digital-strategy.ec.europa.eu/en/policies/cra-reporting https://www.cyberresilienceact.eu/news/cra-notified-bodies-rules-apply-11-june-2026.html https://www.techveda.live/2026/07/16/kernel-cves-cyber-resilience-act/ https://www.techveda.live/2026/07/23/upstream-first-bsp-mainline/ https://www.lynx.com/blog/embedded-linux-has-a-lifecycle-problem https://koansoftware.com/ensure-cra-compliance-for-linux-embedded-devices/ https://nmi.nl/cra-assessment-capacity-lab-scarcity/ https://www.keysight.com/blogs/en/tech/nwvs/2025/09/11/one-year-countdown-to-eu-cra-compliance-september-11-2026-changes-everything https://github.com/CycloneDX/cyclonedx-dotnet/issues/1109 https://github.com/PatchMon/PatchMon/issues/898 https://github.com/relusion/CycloneDX.CRA.Validator https://github.com/sbom-tool/sbom-tools
A7: funded-claim-detection-for-casualty | B7: Funded-Claim Detection for Casualty Reserving | C7: Yes | D7: 6 | E7: Search-backed | F7: =IFERROR(INDEX('Screening Scores'!$I:$I,MATCH($A7,'Screening Scores'!$A:$A,0)),"") | G7: advance | H7: Third-party litigation funding is the largest unmodeled driver of casualty reserve development, and until 2026 insurers had no way to tell whether a given claim was funded. New state registration statutes just created the raw material. The product is a claim-scoring data utility that fuses the newly public funder registries with docket data, UCC-1 filings, plaintiff-firm network graphs and medical-lien patterns to flag probable funder involvement at first notice of loss, months before it shows up as adverse development. Buyer is P&C carrier and reinsurer claims and actuarial reserving leadership; budget line is claims analytics and reserving, plus the outside counsel spend it directly reduces. The moat is entity resolution through shell layers, which compounds as more states adopt registration. | I7: The registries only became populated in 2026. Georgia's regime commenced 1 January 2026, requiring litigation financiers to register through NMLS with disclosure of any party holding 5% or more of voting shares; West Virginia requires registration with the Secretary of State; and a wave of states including Arizona, Colorado, Kansas, Montana, Oklahoma and Tennessee added disclosure and control provisions in 2025. Senator Grassley's Litigation Funding Transparency Act of 2026 (S.3826) would extend disclosure to class actions, MDLs and large coordinated federal proceedings. EY projects TPLF could add as much as $50B in costs to US insurers over five years, a 4-5% annual loss ratio effect — so the prize scales with the dataset that only started existing this year. | J7: The clearest proof nobody has productized this: Law.com had to file an open records request with the Georgia Department of Banking and Finance in July 2026 to assemble a dataset of who owns Georgia's registered litigation funders. A journalist doing FOIA to build the list means no commercial data provider had it. Verisk and peers publish social-inflation thought leadership and general claims analytics, but the specific, hard work of resolving funder identity through shell layers and linking it to individual open claims is not being done. It is unglamorous, legally sensitive, and demands patience with state registry plumbing — three filters that keep founders out. | K7: Two people: one data engineer, one with casualty claims or reinsurance underwriting background. In 90 days: scrape and normalize the Georgia NMLS registrations and West Virginia Secretary of State filings, resolve beneficial ownership and attorney affiliations, and cross-join to PACER and state docket data plus UCC-1 filings naming those funders as secured parties. Ship it first as a paid quarterly intelligence report — the list of funders, their owners, their affiliated firms and their visible case footprint — to a handful of casualty reinsurers and excess carriers, who will buy a list long before they will buy an API. Productize as real-time claim scoring once two or three of them are renewing. | L7: Revealed enterprise demand — what large organizations are actively trying to buy or staff for, where no good vendor exists | M7: https://www.law.com/dailyreportonline/2026/07/17/dataset-who-owns-georgias-litigation-funders/ https://www.hklaw.com/en/insights/publications/2025/05/litigation-funding-in-georgia https://sos.wv.gov/consumer-litigation-financing https://www.congress.gov/bill/119th-congress/senate-bill/3826/text https://www.insidepoliticallaw.com/2026/02/26/senator-grassley-introduces-legislation-requiring-disclosure-of-foreign-third%E2%80%91party-litigation-funding/ https://natlawreview.com/article/georgia-enacts-sb-69-litigation-funding-now-regulated-discoverable-and-subject
A8: grid-equipment-slot-forward-exchange | B8: Forward exchange for transformer and switchgear production slots | C8: Yes | D8: 7 | E8: Search-backed | F8: =IFERROR(INDEX('Screening Scores'!$I:$I,MATCH($A8,'Screening Scores'!$A:$A,0)),"") | G8: advance | H8: Transformers, switchgear and turbines are now the binding constraint on roughly $750B of annual AI datacenter capex, and manufacturers hold production slots against a 10-30% deposit. That makes a slot a de facto option contract with no market, no price discovery, no verification and no way to resell when a site dies — and everybody over-orders, double-booking slots across two or three manufacturers as insurance, so a large stock of paid-for slots is already orphaned. Build the clearinghouse: verified slot listings confirmed directly with the OEM order desk, standardized spec templates (kVA, voltage class, impedance, delivery window), escrow, assignment paperwork, and eventually a forward curve on MVA by delivery quarter. The monetizable fact is that half the announced projects will never break ground. | I8: The gap between announced and constructed capacity blew open in 2026: Sightline Climate tracked 12-16 GW of announced US datacenter capacity for 2026 with only about 5 GW under construction, and roughly $650B was committed to AI datacenters this year against components representing less than 10% of build cost. Lead times went from about 40 weeks pre-pandemic to 24-60 months; substation transformers now run 75-110 weeks and GSU transformers 100-150+ weeks. FERC's 18 June 2026 Show Cause Orders to all six RTOs (Docket RM26-4) force expedited co-location and large-load study processes, which will pull even more simultaneous orders into the queue and deepen the double-booking. By 2029-2031 the orphaned-slot pool is a multi-billion-dollar secondary asset class, and whoever holds the transaction data owns the only real forward curve for grid iron. | J8: The entire investor conversation is about building more transformers — capital-intensive with a 3-5 year payback — or about used-equipment brokerage of physical assets (Transformer Exchange, VAWN lead-time indices), which is old-school and backward-looking. Nobody is trading the forward position. Industry sources openly acknowledge the phantom demand that makes the secondary market necessary: Terrapin's 2026 lead-time report states outright that there is believed to be double booking on transformers and switchgear because of extra-long lead times, which inflates backlogs and hides real availability. GE Vernova's slots are reported tight through 2030 and MV switchgear is described as sold out through 2028 in many channels, yet a large share of announced capacity will never be built — and there is no venue where those slots can change hands. | K8: No product for the first 20 trades. Two people with an energy-procurement background run a brokerage desk: cold-call the roughly 200 datacenter, BESS and utility developers with cancelled or delayed projects, list their slots, match to buyers, take 2-4% and escrow the deposit. Then build the listing and verification product — a slot record confirmed directly with the OEM order desk and standardized on kVA, voltage class, impedance and delivery window. Ninety-day goal: 10 closed assignments and a proprietary dataset of real transacted slot prices that nobody else has, which is the seed of the forward curve. | L8: X / Twitter builder, operator and investor discourse | M8: https://x.com/Filecoin/status/2075002514705883250 https://x.com/aakashgupta/status/2042089628082303254 https://x.com/ExnerPirot/status/2053862056827519087 https://x.com/thexcapitalist/status/2016480187790065829 https://x.com/charlierybak/status/2054032549630931430 https://terrapincg.com/news/switchgear-transformer-generator-lead-times-2026 https://build.inc/insights/data-center-transformer-procurement-2026 https://www.power-eng.com/gas/turbines/data-centers-drive-record-surge-in-ge-vernova-power-equipment-orders-as-turbine-slots-tighten-through-2030/ https://www.ferc.gov/rm26-4 https://www.morganlewis.com/blogs/powerandpipes/2026/07/ferc-presses-grid-operators-on-data-center-large-load-interconnections
A9: stateful-hash-signature-key-state-custody | B9: Key-state custody for LMS/XMSS firmware signing under CNSA 2.0 | C9: Yes | D9: 8 | E9: Recall-only | F9: =IFERROR(INDEX('Screening Scores'!$I:$I,MATCH($A9,'Screening Scores'!$A:$A,0)),"") | G9: borderline | H9: CNSA 2.0 mandates the stateful hash-based schemes LMS and XMSS — not ML-DSA — for software and firmware signing, and NIST SP 800-208 requires key generation and signing to happen inside a FIPS 140 Level 3 HSM with one-time keys that are never reused. That converts code signing into a crash-consistent distributed-state problem the industry has never had to solve: one HSM clone, DR failover, backup restore, CI rerun or parallel build job can silently and permanently destroy a device root of trust. Build the state custodian: a signing API in front of cloud HSMs that allocates monotonic indices under a replicated ledger, reserves disjoint HSS/XMSS-MT subtrees per builder so parallelism can never collide, refuses to sign on ambiguous state, and emits a tamper-evident index-usage log plus the audit evidence that no index was ever reused. | I9: CNSA 2.0 says new firmware/software releases for National Security Systems should already have been signed with CNSA 2.0 algorithms by 2025; from 1 January 2027 all new NSS acquisitions must support CNSA 2.0, and classical-only signatures are not accepted by 2030 — 1 January 2027 is the point where guidance becomes a procurement gate, and the requirement flows down contractually to the defense industrial base. On the civilian side, OMB M-26-15 (24 June 2026, issued under the June 2026 executive order) sets a five-phase federal migration through 2035 with agency PQC migration plans due October 2026, and NIST IR 8547 deprecates RSA/ECDSA after 2030 and disallows them after 2035. Note one discrepancy in the raw material worth verifying before acting: the June 2026 executive order is cited as EO 14412 by one source and EO 14409 by another. Silicon and bootloaders architected in 2026 ship in 2028-2030 and stay in the field to roughly 2045, so the decision is being made now and cannot be re-made later. | J9: Essentially all post-quantum discourse and product is ML-KEM/ML-DSA in TLS, plus crypto discovery and inventory (Venafi, Keyfactor, QuSecure, SandboxAQ); a GitHub search for XMSS/LMS hash-based signatures returns exactly one repository — a 4-star academic VHDL artifact from a university chair, last touched 2026-02-12 — while CBOM/inventory tooling is already productised (cbomkit at 121 stars, awesome-post-quantum at 499). Stateful signatures are treated as an HSM vendor footnote; guidance itself notes that not all HSMs supporting ML-DSA support the stateful schemes and that state-persistence semantics differ per vendor, so there is no portable answer. The failure mode — state exhaustion and index reuse under backup/restore — is an operations problem, so cryptography vendors underrate it and sell HSMs or advisory hours instead. | K9: 1-3 people, 90 days. Ship an open-source LMS/XMSS state manager: a small daemon fronting PKCS#11 HSMs that hands out signature indices under a Raft-replicated ledger, implements SP 800-208 state partitioning (disjoint subtrees per CI runner), refuses to sign on ambiguous state, and emits a tamper-evident index-usage log — plus an open-source verifier and MCUboot/U-Boot reference code so customers can validate independently. Free wedge: a 'state fork detector' that scans an existing signing log for reuse. Sell the hosted multi-region control plane and the audit report first to defense-industrial-base and embedded/industrial OEMs who have just found CNSA 2.0 flow-down clauses in contracts or are failing CNSA 2.0 questions in RFPs, and to the ODMs who sign firmware on their behalf. Drop-in integrations for Yocto, Zephyr, MCUboot and U-Boot are the adoption surface. | L9: Hacker News + technical community consensus and its blind spots; The dated regulatory and standards pipeline — compliance deadlines landing 2027-2031; Developer, protocol, data and standards-layer gaps (GitHub-as-primary-source sweep) | M9: https://csrc.nist.gov/pubs/sp/800/208/final https://nvlpubs.nist.gov/nistpubs/SpecialPublications/NIST.SP.800-208.pdf https://media.defense.gov/2025/May/30/2003728741/-1/-1/0/CSA_CNSA_2.0_ALGORITHMS.PDF https://www.thalestct.com/wp-content/uploads/2024/01/quantum-resistant-code-signing-wp-1-18-24.pdf https://www.wolfssl.com/special-rules-for-lms-and-xmss/ https://www.encryptionconsulting.com/future-of-code-signing-with-cnsa-2/ https://pqcmandates.com/mandate/nist-sp-800-208 https://www.whitehouse.gov/wp-content/uploads/2026/06/M-26-15-Execution-of-the-Migration-to-Post-Quantum-Cryptography.pdf https://nvlpubs.nist.gov/nistpubs/ir/2024/NIST.IR.8547.ipd.pdf https://www.safelogic.com/blog/cnsa-2.0-and-the-2027-inflection-point https://postquantum.com/security-pqc/omb-m-26-15-pqc-migration/ https://www.hstoday.us/subject-matter-areas/cybersecurity/omb-issues-federal-roadmap-for-post-quantum-cryptography-migration/
A10: copper-retirement-life-safety-circuits | B10: Copper sunset triage for fire-alarm, elevator and area-of-refuge lines | C10: Yes | D10: 9 | E10: Recall-only | F10: =IFERROR(INDEX('Screening Scores'!$I:$I,MATCH($A10,'Screening Scores'!$A:$A,0)),"") | G10: borderline | H10: When a carrier retires a wire center, every copper POTS line it serves dies at once — and the lines that die are not phones, they are fire-alarm DACT circuits, elevator emergency phones and ADA area-of-refuge phones that building codes legally require to work (NFPA 72, ASME A17.1). Ordinary VoIP is not a substitute because it corrupts the Contact ID and SIA signaling tones a fire alarm communicator uses to report. Build the national data layer nobody owns: carrier copper-retirement and §214 discontinuance filings normalized to wire-center level, geocoded and joined to commercial property, elevator permit and fire-inspection records, so you can tell a portfolio owner 'these 42 buildings lose POTS within 90 days, here are the devices at risk.' Monetize as a per-line compliance registry — code-obligation mapping, sequenced cutover runbook, and an inspector-ready signed documentation packet — with managed cutover referred through the integrators who already hold the building relationship. | I10: The FCC voted on 26 March 2026 to streamline copper wire-center retirement and declined to impose any compatibility requirement on replacement services, having already cut the notice period from 180 to 90 days — and Section 214 relief means carriers now give notice rather than seek approval. Ninety days is not enough for a facilities manager to inventory dependent systems, source a vendor, install, test and get re-inspected. AT&T began decommissioning roughly 500 wire centers (about 10% of its footprint) from June 2026 targeting effectively full copper retirement by 2029, with a November 2026 filing seeking to discontinue POTS for approximately 90,000 customers across 18 states; Verizon, Lumen, Frontier and CenturyLink have filed their own 2026-2029 retirement notices. Pricing forces action independently: POTS line rates are rising more than 30% per year, with single lines reaching $500-$2,700/month. | J10: The visible market is hardware vendors selling a box (Ooma AirDial, DataRemote, MetTel, Granite) and thousands of local integrators doing reactive, door-to-door truck rolls. Nobody owns the layer above: a per-line risk registry keyed to wire-center retirement filings, mapped to the specific code obligation and the AHJ that will actually inspect it. Search turns up essentially one thin player (CopperAlerts) doing any form of wire-center alerting. It is invisible to software investors because it reads as a telecom reseller business, and invisible to telecom because it is a compliance-documentation business; HN treats POTS as a nostalgia topic rather than a live building-code emergency. (Evidence caveat: both scouts were blocked from opening pages directly, so URLs and quotes are search-extract level.) | K10: 90 days, 1-3 people: scrape and normalize carrier copper-retirement and §214 discontinuance notices into a wire-center-level database, join to a CLLI/NPA-NXX lookup and to commercial property, elevator permit and fire-inspection datasets, and ship a free 'is my building in the blast radius' checker that takes a list of phone numbers or addresses. Convert to a paid per-line registry: line inventory, NFPA 72 / A17.1 obligation mapping, cutover runbook, and a signed documentation packet for the fire marshal or elevator inspector. First customers are portfolio owners with concentrated exposure and mandatory inspection cycles — hospital systems, school districts, senior living operators, REITs — sold alongside the fire-alarm integrators and elevator maintenance companies who are currently tracking this in spreadsheets and will refer deals to get the paperwork off their desks. | L10: Reddit / unglamorous-trades practitioner lens (search-level evidence only; WebFetch blocked); Hacker News + technical community consensus and its blind spots | M10: https://www.phonewire.com/blog/30958 https://www.vcomsolutions.com/blog/copper-sunset-fcc-2026-order-pots-lines https://copperalerts.com/fcc-copper-retirement-march-2026 https://www.ooma.com/blog/business/att-copper-shutdown-pots-phaseout-2025-2029/ https://dataremote.com/blog/elevator-emergency-phones-after-copper https://ipfone.com/when-copper-disappears-who-answers-the-elevator https://rcntechnologies.com/fcc-section-214-passed-pots-replacement-government-agencies/ https://101voice.com/the-pots-sunset-timeline/ https://facpmanuals.com/blog/fire-alarm-communicators-2026 https://rcntechnologies.com/pots-line-replacement-checklist/ https://www.idealbusiness.io/ideal-business-advisors-blog/the-copper-deadline-just-got-real-whats-changed-since-last-year
A11: cui-determination-for-machine-shops | B11: CUI determination and marking for small defense machine shops | C11: Yes | D11: 10 | E11: Search-backed | F11: =IFERROR(INDEX('Screening Scores'!$I:$I,MATCH($A11,'Screening Scores'!$A:$A,0)),"") | G11: advance | H11: Every CMMC vendor sells the enclave — GCC High, managed SIEM, a policy binder — but almost none solve the step that actually fails assessments: a 30-person machine shop cannot tell which of the thousands of drawings, travelers, quotes and emails moving through it is Controlled Unclassified Information. Build a determination-and-marking engine that ingests customer drawings and PDFs, reads DoD distribution statements and DFARS flow-down clauses, decides CUI vs FCI vs neither, applies correct markings, and emits shop-floor labels and a defensible audit trail for the traveler packet. Sell it through CMMC consultancies as the tool they hand every client at scoping. | I11: The 48 CFR CMMC acquisition rule was published in the Federal Register on September 10, 2025 and took effect November 10, 2025, converting CMMC from guidance into a binding contract clause for primes and subcontractors alike. Phase 1 (Nov 2025 through late 2026) is self-assessment; the phase requiring third-party Level 2 certification begins around November 2026 and ramps over three years, so the certification wave hits the long tail of tens of thousands of small shops across 2027-2029. Subcontractors touching CUI must meet the same bar as primes or lose the award, and small contractors face $20k-$100k+ in compliance cost. It is a mandatory purchase with an already-effective legal trigger. | J11: The market has decided CMMC is an IT-infrastructure purchase, so money and attention flowed to enclaves and MSSPs. But missing or incorrect CUI marking keeps showing up among the top findings in 2025-2026 reviews, and 'we don't have CUI' remains a near-universal and near-universally wrong belief among active DoD subcontractors. The real failure mode is document classification and physical shop-floor labeling, not networking, which is precisely why an MSP-shaped industry is structurally blind to it. The tell: the best available how-to material is a self-published Amazon guide and blog posts from label vendors — no software product owns this. | K11: 90 days: a drop-a-folder desktop/web tool that parses distribution statements B through F, export-control markings and DFARS 252.204-7012 flow-down language out of PDFs and CAD title blocks, then emits a per-file CUI determination with written rationale, a marking overlay, a printable CUI cover sheet and a shop-floor label. First customer is not the machine shop — it is the CMMC consultancy and C3PAO-adjacent advisor doing this by hand today; it is the most-billed and least-automated hour in their scoping engagement, so they will resell it. Land 10 consultancies, reach a few hundred shops. | L11: Reddit / unglamorous-trades practitioner lens, run WITHOUT working fetch. METHOD CAVEAT: the scout's egress gateway returned HTTP 403 on CONNECT for every host attempted, so WebFetch was unusable and WebSearch refuses reddit.com outright; no verbatim practitioner quotes could be captured, and signal_quotes were deliberately omitted rather than fabricated. Every URL is real and surfaced by WebSearch, but evidence is SEARCH-LEVEL, NOT PRIMARY-VERIFIED — dates and claims should be re-verified before acting. Substitute method: chased the same substance (unglamorous operators, dying workflows, spreadsheets running real money) through dated regulatory triggers, sunset notices and agency rulemakings reachable by search. | M11: https://www.stealthtech365.com/insights/cui-identification-and-marking-the-step-most-defense-contractors-get-wrong-before-cmmc/ https://www.defenseandmunitions.com/article/controlled-unclassified-information-cui-in-a-manufacturing-plant/ https://www.bdo.com/insights/advisory/defense-contractors-new-reality-the-final-48-cfr-rule-is-bringing-cmmc-into-federal-acquisition https://www.preveil.com/blog/cmmc-final-rule-published/ https://cmmcdashboard.com/blog/cmmc-48-cfr-final-rule-small-defense-contractors https://petronellatech.com/blog/what-dod-instruction-implements-the-cui-program-dodi-5200-48-explained-for-defense-contractors/
A12: rec-state-packaging-epr-reporting-for-mid-market-brands | B12: State packaging EPR reporting for mid-market brands | C12: Yes | D12: 11 | E12: Thin | F12: =IFERROR(INDEX('Screening Scores'!$I:$I,MATCH($A12,'Screening Scores'!$A:$A,0)),"") | G12: advance | H12: California, Oregon, Colorado, Minnesota, Maryland and others have enacted extended producer responsibility laws for packaging, each requiring producers to report every SKU's packaging by material type, weight, and recyclability into a producer responsibility organization, then pay eco-modulated fees. A mid-size food or consumer brand with 400 SKUs has no idea what its cartons weigh. This is grinding, unglamorous data assembly with a statutory deadline per state. | I12: Reporting obligations and fee assessments began phasing in 2025-2026 with more states stacking on through 2029-2031, and each new state adds a differently-shaped report against the same underlying SKU data — which is the classic wedge for a single system of record. Verify current deadlines per state and Circular Action Alliance's reporting calendar. | J12: [UNVERIFIED — no live web access this session; confirm before acting] This is explicitly NOT carbon accounting — it is per-SKU packaging bill-of-materials data, a different dataset with a different buyer (packaging engineer and regulatory affairs, not the sustainability team). The ESG software crowd went to emissions. Large CPGs hired consultants. The 50-500 SKU brands, which number in the tens of thousands, have nobody. | K12: Build a packaging BOM database seeded by asking brands to ship you one of each package and physically weighing and characterizing it — an unscalable manual step that is also the moat, because the data doesn't exist anywhere. Charge $10-25k for first-year data assembly plus filings across all mandated states, then annual maintenance. Sell through co-packers and packaging distributors, which touch hundreds of brands each. | L12: boring-cashflow | M12: https://calrecycle.ca.gov/packaging/ https://www.oregon.gov/deq/recycling/Pages/Recycling-Modernization-Act.aspx https://circularaction.org/
A13: part-146-bvlos-data-services | B13: Part 146 ADSP certification: strategic deconfliction plus the sub-400-foot obstacle layer | C13: Yes | D13: 12 | E13: Recall-only | F13: =IFERROR(INDEX('Screening Scores'!$I:$I,MATCH($A13,'Screening Scores'!$A:$A,0)),"") | G13: borderline | H13: The FAA's BVLOS rulemaking creates a brand-new federally certificated business category — Automated Data Service Providers under proposed Part 146, separately authorized for strategic deconfliction, conformance monitoring, and supplemental data services. Every routine BVLOS flight, and mandatorily every operation over open-air assemblies, must buy from a certificated ADSP, which is a licensed toll position on US low-altitude airspace with no established winner. The visible entrants (ANRA, SkyGrid) are all racing at deconfliction because it is the glamorous algorithmic part; the supplemental-data lane is nearly empty, and the thing that lane needs — a survey-grade, continuously refreshed national database of sub-400-foot obstacles (distribution power lines, guy wires, transmission spans, met towers, temporary cranes) that existing FAA obstacle data does not resolve — is the input the deconfliction players will have to source rather than build. Sell the obstacle layer into utility, rail and pipeline drone-inspection budgets today; certify it as a Part 146 supplemental data service when the rule lands. | I13: The Administration directed the FAA to publish a final BVLOS rule by 1 February 2026; the government shutdown pushed it toward a March 2026 timeframe and the comment period was reopened; the final rule reached OIRA for review on 10 July 2026, with publication most likely late 2026 or into 2027. Certification takes time, so whoever is already collecting data, running software and holding operator relationships during the implementation window holds the first certificates, with the revenue curve landing 2028-2031 as routine delivery, infrastructure inspection and public safety BVLOS scale. HONEST RISK: this publication date has slipped repeatedly and could slip again into 2027 — of the dated triggers in this set, this is the softest. | J13: Software founders filed drones under 'failed 2016 hype cycle' and stopped reading, so the entire discussion sits in drone trade press and aviation law firm alerts rather than general technology media — the classic profile of an overlooked licensed market. Within the industry, commentary explicitly calls Part 146 'the real disruptor in the NPRM' that the industry is not taking seriously, and what attention exists is concentrated on deconfliction. Supplemental data services get dismissed as a commodity feed; building the obstacle database looks like fieldwork and a mapping company rather than a software company, which repels the typical founder. That mismatch between perceived and actual difficulty is the entire opening. | K13: Do not attempt national coverage. 90 days: pick electric distribution rights-of-way in two or three states, assemble the obstacle layer from utility LiDAR the utilities already own but do not exploit, crowd-sourced flight telemetry, and targeted survey, and sell it directly into those utilities' own drone inspection programs — they have budget and an immediate safety need, and that revenue funds coverage expansion. In parallel, run strategic deconfliction and conformance monitoring as a free/low-cost API built against the published Part 108/146 requirements, integrated with existing Part 107 waiver operators and drone flight software, purely to accumulate flight data and operator dependence before certification exists. The regulatory work runs alongside; the data and the operator network are the moat. | L13: Hacker News / technical-community consensus and its blind spots; Revealed enterprise demand — what large organizations are actively trying to buy or staff for | M13: https://www.crowell.com/en/insights/client-alerts/landmark-proposed-rule-may-open-american-skies-to-expanded-commercial-drone-deployments https://pilotinstitute.com/part-108-explained/ https://insideunmannedsystems.com/faa-reopens-part-108-bvlos-comment-period/ https://aerovisionglobal.com/blogs/news/faa-part-108-deadline-update-expected-march-2026 https://www.herrick.com/publications/part-108-and-pro-sports-how-the-faas-bvlos-proposal-could-impact-stadium-operations-broadcasting-and-event-partnerships/ https://sky.trade/articles/bvlos-part-108-2026 https://www.faa.gov/newsroom/BVLOS_NPRM_website_version.pdf https://www.npuasts.com/news/article/opinion-part-146-is-the-real-disruptor-in-the-nprmand-why-the-industry-must-take-it-seriously https://www.commercialuavnews.com/part-108-part-146-bvlos-autonomous-drone-operations https://www.anratechnologies.com/home/2025/08/29/anra-technologies-is-ready-for-part-146/ https://www.thedronegirl.com/2025/08/08/part-146/
... A26: lead-service-line-inventory-2027 | B26: Killing lead-line 'unknowns' before the Nov 1, 2027 LCRI baseline locks in | C26: Yes | D26: 25 | E26: Recall-only | F26: =IFERROR(INDEX('Screening Scores'!$I:$I,MATCH($A26,'Screening Scores'!$A:$A,0)),"") | G26: cut | H26: Under the Lead and Copper Rule Improvements, every public water system must hold a baseline service-line inventory by 1 November 2027 covering all lines and connectors regardless of ownership, publish a replacement plan, update it annually, and notify affected customers individually. Lines still classified 'unknown' are treated as lead, and the 2027 baseline locks in the mandatory replacement rate (roughly 10% of remaining inventory per year) and schedule for the following decade — so every unknown you reclassify correctly before the deadline is thousands of dollars of avoided capital, times an estimated 3.5-6.6 million unknown lines nationally. The business sells that arbitrage two ways: an outcome-priced 'unknowns reduction' engagement for mid-size utilities (predictive targeting model plus subcontracted vacuum-excavation potholing plus the regulatory documentation package), and a $200/month self-serve version of the paperwork for the tens of thousands of tiny systems run by a part-time operator who also drives the plow truck. | I26: 1 November 2027 is the statutory compliance date for the baseline inventory, the lowered 10 ppb action level, updated sampling plans and the school/childcare list — and the practical deadline is earlier, because unknowns must be resolved by field verification, which takes dig seasons. After that date most systems must replace covered lines within ten years, with all lead service lines replaced by 1 November 2037 and remaining unknowns validated by 2034, so the annual reporting, notification and progress-tracking obligation runs continuously for a decade. Systems serving 3,300 or fewer people plus all NTNCWSs get an alternative route that still requires proving 100% replacement of lead and galvanized-requiring-replacement lines at a minimum annual rate within five years — a documentation obligation, not relief. The scale of remaining ambiguity is measurable: Wisconsin Watch reported in June 2026 that more than 181,000 Wisconsin service lines, about 12% statewide, are still classified unknown. | J26: 120Water, BlueConduit and Trinnex took the top of the market — municipalities with GIS staff, consultants and capital budgets. Below that, the very small community systems and non-transient non-community systems (schools, mobile home parks, small manufacturers on their own wells) are numerically the majority and commercially invisible: no procurement process, no conference presence, ACVs too small for an enterprise sales motion, and currently running on paper and Excel toward default non-compliance. At the mid-market, the specific procurement insight — that the composition of the 2027 baseline determines a decade of obligations, so verification spend in 2026-27 has a computable ROI — is being executed by regional engineering firms billing hourly; nobody has packaged it as outcome-priced work. (Evidence caveat: both scouts hit a hard egress block and could only work at search-extract level, so dates and figures below are strong leads, not page-verified citations.) | K26: Two people plus one subcontracted hydro-excavation crew, 90 days, one state. Build the predictive unknowns model from public data (parcel age, permit records, prior dig results), and sell a fixed-price 'unknowns reduction' engagement to five mid-size utilities priced as a share of avoided replacement obligation. In parallel ship the paperwork product that funds distribution: spreadsheet-import-first, takes whatever the operator has, structures it to the EPA inventory template, generates the public inventory page and annual replacement-plan document, and sends the individually-required customer notifications with delivery evidence — priced self-serve. Distribution for the small-system tier is state primacy agencies and rural water associations, which are already fielding these questions with no tool to point operators toward. | L26: Reddit / unglamorous-trades practitioner lens (search-level evidence only; WebFetch blocked); Physical world — industry, energy, grid, water, logistics, materials, construction (search-level evidence only) | M26: https://www.epa.gov/ground-water-and-drinking-water/lead-and-copper-rule-improvements https://www.epa.gov/system/files/documents/2024-10/final_lcri_faq_statespws.pdf https://www.cdmsmith.com/en/resources/insights/lead-and-copper-rule-improvements-faq https://www.nlc.org/article/2024/11/01/understanding-new-lead-and-copper-rule-requirements-for-local-governments/ https://www.mass.gov/info-details/lead-and-copper-rule-improvements https://www.ae2s.com/perspectives-and-insights/lead-and-copper/ https://www.freese.com/lead-and-copper-rule-compliance-countdown-strategic-planning-for-2027-deadline https://www.epa.gov/system/files/documents/2024-10/final_lcri_fact-sheet_deferred-deadlines.pdf https://www.nrdc.org/press-releases/nrdc-estimates-12-million-lead-pipes-may-connect-water-mains-homes-most-states-fail https://wisconsinwatch.org/2026/06/wisconsin-lead-pipe-count-falling-water-service-line-system-data-health-environment/ https://www.bdlaw.com/publications/epa-issues-final-lead-and-copper-rule-improvements-with-far-reaching-lead-pipe-replacement-mandates/ https://www.ldh.la.gov/assets/oph/Center-EH/engineering/LCRI/LCRI-FAQs_05.21.2026.pdf
A27: 340b-rebate-covered-entity-side | B27: The Covered-Entity Side of the 340B Rebate Flip | C27: No | E27: Search-backed | F27: =IFERROR(INDEX('Screening Scores'!$I:$I,MATCH($A27,'Screening Scores'!$A:$A,0)),"") | G27: cut | H27: HRSA's 340B Rebate Model Pilot inverts a 30-year-old mechanic: hospitals and clinics will buy at wholesale acquisition cost and then submit claims-level data to manufacturers to claw the discount back as a rebate. Every dollar of software money so far has gone to the manufacturer side, leaving the covered entity with a submission, tracking, dispute and reconciliation problem plus a brand-new cash-flow hole. The product is a rebate-claim engine wired into pharmacy dispensing and split-billing systems with a 45-day-per-claim deadline tracker, and — the real prize — working-capital financing advanced against pending 340B rebate receivables. Buyer is the hospital or FQHC 340B program director and pharmacy finance lead; budget line is 340B program savings, which for many safety-net hospitals is the operating margin. | I27: HRSA paused the model for court reasons and reset the pilot to start 1 January 2027. Manufacturers had to submit claims-collection and rebate-issuance plans by 24 August 2026 with approvals around 24 September 2026, and HRSA has published notice contemplating expansion to roughly 25 products from 13 manufacturers. The operational forcing function is the 45-calendar-day window from date of dispense to submit data and claim a rebate. HRSA's own estimate is roughly 15,250 covered entities carrying nearly 4 million hours of annual burden, about 260 hours per entity — a recurring operational load that arrives on a fixed date. | J27: The vendor landscape is entirely manufacturer-facing. Kalderos, the platform manufacturers proposed to use to administer rebates, was acquired by Model N in June 2026 and folded into life-sciences gross-to-net revenue management; 340B ESP (Second Sight Solutions) is likewise the manufacturer-mandated claims-data platform; Craneware and peers serve split-billing and compliance, not rebate claiming or the resulting cash-flow gap. Providers are publicly objecting to the administrative burden rather than buying anything — because there is nothing to buy. Model N's own 2026 State of Revenue Report reports only 1% of life sciences revenue leaders have real-time visibility into 340B discounts and rebates, so even the funded side of the market is immature. | K27: A two-to-three person team, one of whom knows pharmacy 340B split-billing plumbing. In 90 days: build the claims-extraction and rebate-submission connector for one or two of the most common dispensing/split-billing systems, wrap it in a 45-day-per-claim deadline tracker with per-claim status and manufacturer dispute handling, and pilot with 5-10 DSH hospitals or FQHC networks that already know the cash-flow hit lands 1 January 2027. First customer is a multi-site FQHC network whose 340B savings fund clinical staffing. Financing starts as simple factoring against validated, submitted claims once the data pipeline is trusted. | L27: Revealed enterprise demand — what large organizations are actively trying to buy or staff for, where no good vendor exists | M27: https://www.federalregister.gov/documents/2026/02/17/2026-03042/request-for-information-340b-rebate-model-pilot-program https://www.hfma.org/operations-management/340b-rebate-model-hospital-burden/ https://www.forvismazars.us/forsights/2026/07/hrsa-takes-steps-to-implement-a-340b-rebate-model https://www.modeln.com/company/news/press-center/model-n-acquires-kalderos-to-expand-its-340b-capabilities-and-gross-to-net-revenue-management/ https://www.fiercehealthcare.com/providers/revised-340b-rebate-model-pilot-program-moves-forward-despite-provider-pushback https://rwc340b.org/hrsa-publishes-notice-contemplating-expanding-340b-rebate-model-to-13-manufacturers-and-extends-rebate-rfi-comment-deadline/
A28: ai-exclusion-gap-insurance-layer | B28: AI exclusion gap diagnosis for commercial insurance buyers | C28: No | E28: Search-backed | F28: =IFERROR(INDEX('Screening Scores'!$I:$I,MATCH($A28,'Screening Scores'!$A:$A,0)),"") | G28: cut | H28: On January 1, 2026 ISO endorsements CG 40 47, CG 40 48 and CG 35 08 went live, letting carriers strip generative-AI claims out of standard commercial general liability, and at least six major carriers have since filed their own non-standard AI exclusions with state regulators. Every commercial renewal now carries bespoke exclusion wording that no broker can read consistently across a book of business. Build the buy-side diff-and-gap layer: parse the policy, detect the exclusion form and its manuscript variants, quantify the gap against what the insured actually does with AI, and route the client to write-back endorsements or affirmative AI markets. The proprietary corpus of exclusion wordings you accumulate is the moat. | I28: The break is dated and simultaneous rather than gradual: the ISO endorsements took effect January 1, 2026, and AIG, WR Berkley and Great American filed their own exclusions in 2026 on top of Berkshire Hathaway and Chubb, which already had approval. Because commercial policies renew annually, 100% of the US commercial market passes through this diagnosis by the end of 2027. The second-order trigger is contractual: as enterprises start demanding affirmative AI coverage from software and services vendors, a new certificate-of-insurance attestation surface appears, which is the 2029-2031 platform. | J28: Capital and attention all went to the underwriting side — new AI liability MGAs and carrier products, including HSB's AI Liability Insurance launched March 2026. Nobody is arming the 36,000+ US retail brokerages and the risk managers who must now explain to a board why the GL policy no longer covers the thing the company just automated. Policy-language comparison was tried as 'insurtech document AI' around 2021, dismissed as non-venture-shaped, and abandoned — but the trigger changed the unit economics, because the diff now has a dollar value attached and a placement fee behind it. | K28: One insurance-literate operator plus one engineer. Ship a parser that detects CG 40 47 / CG 40 48 / CG 35 08 and their manuscript equivalents in a PDF policy, outputs a one-page 'what you just lost' memo in plain language, and maps the gap to available write-back endorsements and affirmative AI markets. Give it to brokers free so it wins them placements, and charge per submission or take a share of the write-back placement. Ninety-day target: 30 brokerages live, a growing corpus of carrier AI wordings, and a public wording tracker that gets you cited every time a new carrier files. | L28: X / Twitter builder, operator and investor discourse, harvested via site:x.com search (direct WebFetch to x.com and most primary sites was blocked by proxy policy) and cross-validated against dated primary sources: Federal Register notices, SCOTUS opinions, EU directives, CBP data, FMCSA rules, ISO insurance form filings and industry lead-time indices. Bias toward operators over commentators and toward dated 2026-2028 structural triggers. | M28: https://news.bloomberglaw.com/insurance/insurer-ai-exclusions-spark-policyholder-alarm-on-coverage-gaps https://www.policyholderpulse.com/ai-exclusions-insurance-policies/ https://www.theleveragedyears.com/ai-regulation-news/iso-generative-ai-insurance-exclusions-2026 https://todaysgeneralcounsel.com/ai-exclusions-creating-gaps-for-policyholders-fragmenting-insurance-market/ https://insuranceintel.substack.com/p/chubb-is-excluding-the-risk-its-own https://www.businessinsuranceusa.com/blog/insurance/ai-coverage-gap-small-business-insurance-2026/ https://phl-firm.com/generative-ai-insurance-exclusions-2026/
A29: analog-media-supply-chain | B29: Graded, Warrantied Refurbished Film Cameras — the CarMax of Analog | C29: No | E29: Thin | F29: =IFERROR(INDEX('Screening Scores'!$I:$I,MATCH($A29,'Screening Scores'!$A:$A,0)),"") | G29: cut | H29: Film photography, vinyl and instant film have grown for roughly a decade on a durable authenticity and status shift, but the binding constraint is now supply chain, not demand: film-camera repair technicians are retiring without replacements, used body prices have multiplied, and mail-in labs run backlogged. Build the branded refurbished-camera business — buy dormant bodies at near-scrap through estate and bulk channels, service them to a published condition grade, sell DTC with a real 12-month warranty. Attach rentals for the try-before-buy segment and a develop-and-scan subscription once volume justifies the chemistry. The moat is trained repair labor and consistent grading, neither of which an eBay seller can produce. | I29: Be plain: the raw material contains no verified dated or numeric trigger. The strongest claims — that the Gen Z film cohort is now roughly a decade deep, that on the order of a hundred million dormant film bodies sit in closets, and that tariffs raised new-camera prices and widened the refurb spread — are all reasoned from the scout's own knowledge with no dated source and no live verification. The structural argument that does not depend on a trigger: the scarce input is repair skill, which can be taught in months, while the raw input (dormant bodies) is enormous and priced at near-scrap. That arbitrage is timeless rather than time-boxed, which is honestly an argument for lower urgency, not higher. Verify RIAA vinyl unit trends and used-body price series before sizing. | J29: It reads as hardware, low-margin and structurally unfundable by venture standards, so it stays fragmented across eBay listings and one-person repair benches with six-month queues. The demand is dismissed as nostalgia rather than recognized as a durable status good — which is precisely the misread that keeps the field empty long enough for a patient operator to consolidate it. Note: the scout had no live verification, so 'the field is empty' is a hypothesis; competitive diligence against existing refurb sellers and lab chains is the first check. | K29: Days 1-30: narrow to three high-volume models with well-documented service procedures and deep parts availability (the Canon AE-1 / Pentax K1000 / Olympus OM tier), because repeatability in repair is the entire unit economics. Buy 300-500 bodies through estate sales, camera-store liquidations and bulk lots at $10-40 each. Days 30-60: train two technicians on those three models only — not general repair — and write a five-tier published condition grade with photos. Days 60-90: sell on a plain Shopify storefront with a 12-month warranty, priced $150-350, and publish the grading standard as content; the warranty and the standard are the product, since the customer's actual pain is eBay risk. Lab and rentals wait until refurb throughput exceeds roughly 100 units a month. | L29: Consumer behavior, culture, and status shifts with commercial consequences | M29: https://www.riaa.com https://www.ppa.com https://www.ifixit.com
A30: auracast-ada-venue-retrofit | B30: Auracast retrofits sold to venues as assistive-listening compliance, not to consumers as earbuds | C30: No | E30: Search-backed | F30: =IFERROR(INDEX('Screening Scores'!$I:$I,MATCH($A30,'Screening Scores'!$A:$A,0)),"") | G30: cut | H30: Doppler Labs built genuinely good hearing-augmentation hardware and died in 2017 against three constraints: Bluetooth could not do low-latency multi-device broadcast, battery life was inadequate, and there was no regulatory route to sell hearing enhancement without a hearing-aid license. All three are gone — Bluetooth LE Audio and Auracast solved broadcast and latency, the FDA's over-the-counter hearing aid category opened the regulatory path, and mainstream earbuds shipping hearing-aid features normalized the behavior. The move is to flip the customer entirely: sell to venues that carry assistive-listening obligations and currently discharge them with 1990s infrared emitters and induction loops. You are an integrator — survey, size, install, commission, provide the venue-branded receiver app and QR onboarding, and hand the facilities manager a compliance document. | I30: The dated triggers are real but carried from model knowledge and flagged for confirmation: the FDA's OTC hearing aid rule took effect in October 2022; Apple received clearance for a hearing-aid feature on AirPods Pro in 2024; Bluetooth LE Audio and Auracast shipped broadly across Android phones and earbuds through 2023-2025. Confirm each against the FDA and Bluetooth SIG pages before quoting them. The arithmetic that follows is the actual why-now: as receiver penetration in the general population crosses a majority around 2027-2028, venue-side broadcast becomes the cheapest way to satisfy an assistive-listening obligation and the installed base of infrared and loop systems becomes stranded capital on a normal 2029-2031 replacement cycle. Note what is missing: there is no confirmed regulatory effective date requiring Auracast, and if ADA standards never reference it, this is a cost-savings sale rather than a compliance sale. | J30: Hearables as a consumer category is considered settled, and no investor wants another earbud company — a correct verdict that is simply irrelevant to a business selling transmitters and commissioning to stadiums, theaters, houses of worship, airports, transit systems, lecture halls, and gyms. The buyer is an accessibility or facilities manager, a channel with essentially no startup presence; the incumbents are small AV hardware firms with no software capability. Three things were explicitly NOT verified and should be checked in order: whether ADA technical standards have been updated to reference or accept Auracast (this is the load-bearing question — check it first), current Auracast deployment rates in venues, and the size of the assistive-listening retrofit market. | K30: Two people with AV field experience, no hardware development — Auracast transmitters are commodity. In 90 days, productize the survey-to-commissioning workflow for one venue class and do ten installs: houses of worship and municipal council chambers first, because they have small budgets, fast single-decision-maker procurement, existing accessibility obligations, and there are thousands of them within driving distance. Deliverable per site is the transmitter install, coverage map, QR onboarding signage, and a written compliance memo the facilities manager can file. The software layer that turns this from a services shop into a product — channel management, multi-language streams, usage analytics proving the accommodation was used — gets built out of the first ten deployments. | L30: The startup graveyard — great ideas that died for a specific, identifiable reason that no longer applies. | M30: https://en.wikipedia.org/wiki/Doppler_Labs https://www.bluetooth.com/auracast/ https://www.fda.gov/medical-devices/hearing-aids/otc-hearing-aids-what-you-should-know
A31: azole-resistance-hotspot-control | B31: Azole-resistance hotspot mapping and compost protocol certification for green-waste operators | C31: No | E31: Search-backed | F31: =IFERROR(INDEX('Screening Scores'!$I:$I,MATCH($A31,'Screening Scores'!$A:$A,0)),"") | G31: borderline | H31: Pan-azole-resistant Aspergillus fumigatus is manufactured in decomposing plant, wood, and flower-bulb waste treated with agricultural azoles — the TR34/L98H and TR46/Y121F/T289A tandem-repeat mutations are selected there and then arrive in hospitals via air, which is why azole-naive patients present with resistant infections. In 2025 five EU agencies jointly named agricultural and wood waste storage and management as a control point. Nobody sells the control. The business is two products stacked: a paid hotspot surveillance service (sample, culture on azole-supplemented agar, sequence cyp51A, map) sold to composters, biomass yards, bulb growers, and to hospitals and insurers who want to know their catchment risk; and a certified treatment protocol (turning regime, thermophilic hold time, covering) that a site operator can be audited against. | I31: The dated trigger is the 2025 EFSA multi-agency assessment (10.2903/j.efsa.2025.9200), the first time the EU treated environmental azole resistance as a cross-sector regulatory matter, with ECDC, ECHA, EEA, and EMA co-signing and with explicit recommendations on 'proper agricultural and wood waste storage and management' and on approval/renewal of azole fungicides. Be honest about what that is: a formulated recommendation, not a binding rule with an effective date. There is no compliance deadline to sell against yet. The bet is the normal 2-4 year lag from a joint EU scientific opinion to member-state obligations, which puts mandatory hotspot management for large composters plausibly in the 2028-2031 window, and the WHO fungal-priority framing plus resistant-aspergillosis mortality is what makes hospitals willing to pay for catchment data before any rule exists. | J31: The problem sits in the seam between three industries that do not share regulators, customers, or conferences: agrochemicals, waste management, and hospital infection control. No single party carries the liability, so no party buys the fix. The mycology literature has mapped the hotspots for a decade — the Emerging Infectious Diseases study of Danish hot spots and resistance-associated application practices covers 2020-2023 — and yet the entire response today is national advisory guidance in a couple of member states. The scouting search returned zero commercial actors. Caveat on provenance: page fetching was blocked that session, so 'zero commercial actors' is a negative search result, not a verified competitive scan. | K31: One mycologist plus one field tech. In 90 days, sample 40 green-waste, wood-chip, and bulb-waste sites in a single country (the Netherlands, Denmark, or Ireland — small, dense, and already sensitized), culture on azole-supplemented agar, sequence cyp51A for TR34/L98H and TR46/Y121F/T289A, and publish the national hotspot map. The map is simultaneously the paper, the press event, and the lead list — every operator on it now has a named problem and a phone call coming. First paying customer is a large green-waste operator or a bulb-growing cooperative buying a pilot: a baseline survey of their sites plus a controlled trial of one cheap intervention at three of them. That trial output becomes the certifiable protocol you sell repeatedly. | L31: The academic-to-commercial gap: 2024-2026 findings in unfashionable fields (metrology, tribology/corrosion, industrial chemistry, soil/ag science, acoustics, structural biology of non-human organisms, ceramics, NDT) that are replicated and de-risked but unclaimed by any startup. | M31: https://efsa.onlinelibrary.wiley.com/doi/10.2903/j.efsa.2025.9200 https://www.nature.com/articles/s44259-025-00140-0 https://www.ncbi.nlm.nih.gov/pmc/articles/PMC11286046/ https://www.mdpi.com/2309-608X/11/10/731 https://pmc.ncbi.nlm.nih.gov/articles/PMC12565632/ https://www.ncbi.nlm.nih.gov/pmc/articles/PMC11967370/
A32: boot-rom-trust-anchor-retrofit | B32: Trust-anchor retrofit for fleets whose boot ROM can't be changed | C32: No | E32: Recall-only | F32: =IFERROR(INDEX('Screening Scores'!$I:$I,MATCH($A32,'Screening Scores'!$A:$A,0)),"") | G32: cut | H32: Two forced root-of-trust migrations are landing on the same installed base: the 2011 UEFI Secure Boot certificates expiring in 2026, and the CNSA 2.0 / NIST IR 8547 move off RSA and ECDSA before 2030. All published guidance targets IT-managed Windows and RHEL fleets with vendor support contracts; the hard case is the long tail — industrial PCs, medical carts, ATMs, kiosks, POS terminals, network appliances, vehicle ECUs, defense COTS — where the OEM is gone, will never ship a firmware update embedding the 2023 certificates, or has the verification algorithm fixed in immutable boot ROM with no field upgrade path at all. Build the trust-anchor lifecycle layer: a read-only fleet scanner that enumerates PK/KEK/db/dbx state across heterogeneous embedded estates, joins it to a curated model-to-firmware-availability database, and produces a remediation plan plus an attestation artifact an auditor accepts. Convert that into the higher-margin engagement: PQC boot-chain assessments and a hosted stateful-signature (LMS/XMSS, SP 800-208) signing service so a mid-size device maker can issue PQC-signed firmware without building its own PKI. | I32: Microsoft Corporation KEK CA 2011 expired 24 June 2026 and Microsoft UEFI CA 2011 expired 27 June 2026, with Windows Production PCA 2011 following in October 2026 — the failure is silent (devices keep booting but stop receiving signed pre-boot updates) and then catastrophic on a CMOS clear or motherboard RMA, where a system with no 2023-cert firmware release can become unbootable. The June 2026 executive order 'Securing the Nation Against Advanced Cryptographic Attacks' puts federal agencies on a clock — key establishment to NIST standards by 2030, digital signatures by 2031 — cascading immediately to federal suppliers, and the EU's coordinated PQC roadmap requires transition activities to start by end of 2026 with high-risk systems secured by 2030. The CRA's full application on 11 December 2027 turns 'this device can no longer accept signed updates' into a legal product defect for a declared support period. And the physics is unforgiving: a controller or ECU signed in 2026 may still need to verify firmware in 2041, so every unit shipped before the retrofit is a permanent liability. (Note: the raw material cites the June 2026 executive order as EO 14409 here and EO 14412 elsewhere — verify the number before quoting it.) | J32: Every artifact found — Microsoft's Windows IT Pro playbook, Red Hat's advisory, Dell's transition FAQ, Eclypsium's analysis, university KB pages — is written for managed Windows/RHEL fleets and explicitly punts on 'systems with no vendor firmware updates,' which is the population that matters. No product enumerates trust-anchor state across mixed embedded/OT estates via UEFI variables, BMC/Redfish and vendor tooling and maps model to firmware-release availability. The PQC vendor landscape (SandboxAQ, Thales, the PQC Coalition) is organised around enterprise IT discovery, TLS and VPN, sold to a CISO; embedded firmware signing uses different standards and a different buyer (a VP of Engineering at an industrial device maker), and most crypto engineers avoid SP 800-208 because state management is scary. Meta published its multi-year PQC migration and the discussion still centred on inventory and hybrid TLS; the HN response to the Secure Boot expiry was sarcasm ('Updating the Expiring Secure Boot Certificates Is Sure to Go Without a Hitch'), not tooling. | K32: Two embedded-security engineers, 90 days, two products that feed each other. First, a read-only fleet scanner: parse UEFI variables (PK/KEK/db/dbx) via efivarfs on Linux hosts, Redfish/IPMI on servers and vendor tooling on Windows, normalise into a trust-anchor inventory, and join against a hand-curated database of which OEM model has published a 2023-cert firmware release — sell the inventory report to hospitals, manufacturers, retail chains and colo operators, then attach remediation runbooks and a signed attestation artifact. Second, a fixed-scope $25-50k 'PQC boot chain assessment' for industrial controls, automotive tier-1s, medical device makers, energy meters and defense suppliers: enumerate every signature verification point, classify upgradeable versus immutable, and produce a migration plan with LMS/XMSS parameter selection. Target for 90 days: 8 assessments, 2 signing-service design partners, and an open-source SP 800-208 state-management reference that becomes the credibility asset. | L32: X / Twitter builder, operator and investor discourse (cross-validated against dated primary sources); Hacker News + technical community consensus and its blind spots | M32: https://x.com/Meta_Engineers/status/2044806299339096133 https://x.com/NaoXprotocol/status/2070476270069060019 https://promwad.com/news/crypto-agility-long-lifecycle-embedded-devices-pqc-transition https://bluefruit.co.uk/embedded/quantum-safe-embedded-design/ https://www.elektormagazine.com/news/automotive-crypto-agility-ecus https://x.com/HPCwire/status/1928089781881188592 https://www.encryptionconsulting.com/education-center/firmware-signing/ https://techcommunity.microsoft.com/blog/windows-itpro-blog/act-now-secure-boot-certificates-expire-in-june-2026/4426856 https://techcommunity.microsoft.com/blog/windows-itpro-blog/secure-boot-playbook-for-certificates-expiring-in-2026/4469235 https://www.redhat.com/en/blog/expiration-secure-boot-signing-certificates-2026 https://eclypsium.com/blog/microsoft-secure-boot-certificates-expire-2026/ https://www.dell.com/support/kbdoc/en-us/000390990/secure-boot-transition-faq
A33: bridge-power-permit-clock-manager | B33: The 24-Month Clock on Every Bridge-Power Turbine | C33: No | E33: Search-backed | F33: =IFERROR(INDEX('Screening Scores'!$I:$I,MATCH($A33,'Screening Scores'!$A:$A,0)),"") | G33: cut | H33: With grid interconnection and new gas turbine slots gone until 2030, a large share of new data center capacity is being energized on temporary on-site turbines and engines. EPA's stationary combustion turbine NSPS created a conditional exclusion for temporary units capped at 24 months on site — and if a unit stays longer, EPA applies the rule retroactively as though it had always been permanent, putting the operator in immediate noncompliance. The business is the fleet clock: a dated registry of every bridge-power unit and its on-site tenure, sold as a subscription exposure report to data center owners, their lenders and their insurers, with rotation/relocation orchestration and the permanent-source NNSR/Title V fallback application as the services upsell. | I33: The rule published 15 January 2026, so the first cohort of units placed under the exclusion hits month 24 in early 2028, and units deployed through 2026-2027 hit it in 2028-2029 — precisely when grid interconnection for most of these campuses still will not be complete. GE Vernova's turbine book is sold through 2030 with roughly 10 GW remaining across 2029 and 2030 combined (Power Engineering, July 2026), Siemens' large-frame slots are nearly full for 2028, and Mitsubishi has warned new blocks may not ship until the 2030s. That guarantees bridge power sits on site well past 24 months unless somebody manages the rotation. | J33: The bridge-power conversation is entirely about supply and megawatts — VoltaGrid, ProEnergy, Aggreko, United Rentals — while the compliance clock is buried in an NSPS most developers read once for the good news (reduced permit obligations) and never operationalize. Searches surface no product, no tracking system and no service firm. The retroactive-noncompliance mechanic means the liability stays invisible until it is catastrophic, which is the classic shape of an overlooked services market. | K33: An air permitting engineer plus an operations analyst, capital-free. In 90 days: build the registry — scrape state air permit databases, construction notices and rental-fleet deployment announcements to identify temporary turbine and large reciprocating-engine installations at data centers, date-stamp each one, and compute months-to-exposure. First product is a quarterly 'clock and exposure report' per campus; first customers are the lenders and insurers on two or three named Virginia, Ohio or Texas data center projects, who will pay for exposure they cannot otherwise see, followed by the owners themselves once the report lands on their desk. | L33: Physical world — industry, energy, grid, water, logistics, materials, construction, defense-adjacent | M33: https://www.clarkhill.com/news-events/news/epa-turbine-rules-air-permitting-data-centers/ https://encinoenviron.com/epa-closes-permitting-loophole-used-by-ai-data-centers/ https://www.awma.org/blog_home.asp?Display=202 https://www.unitedrentals.com/project-uptime/expertise/guide-planning-bridge-power-systems-data-centers https://www.datacenterfrontier.com/energy/article/55358731/aeroderivative-turbines-move-to-the-center-of-ai-data-center-power-strategy https://www.power-eng.com/gas/turbines/data-centers-drive-record-surge-in-ge-vernova-power-equipment-orders-as-turbine-slots-tighten-through-2030/ https://www.all4inc.com/4-the-record-articles/data-centers-2026-look-ahead/
A34: broker-carrier-credentialing-passport | B34: Carrier-side credential passport after Montgomery v. Caribe | C34: No | E34: Search-backed | F34: =IFERROR(INDEX('Screening Scores'!$I:$I,MATCH($A34,'Screening Scores'!$A:$A,0)),"") | G34: cut | H34: On 14 May 2026 the Supreme Court held 9-0 in Montgomery v. Caribe Transport II that state-law negligent-selection claims against freight brokers survive FAAAA preemption, and brokers tightened carrier vetting within 24 hours. The entire existing vetting stack — Highway, RMIS, MyCarrierPortal, FreightValidate — is broker-side software that treats small carriers as risk to be excluded, and nobody sells anything to the roughly 600k small motor carriers now being locked out. Build the carrier-owned credential: a portable, continuously-attested safety, identity and insurance record the carrier pushes into every broker's vetting system, plus the appeals and correction workflow for when a carrier is wrongly flagged. The by-product — a dataset of which broker and vetting-platform rules actually cause denials — is the wedge back into selling defensible-selection evidence packages to the brokers themselves. | I34: The ruling is dated and unanimous, so there is no circuit split to wait out; Echo Global Logistics' 2024 preemption win was remanded within a week of the decision. Simultaneously, FMCSA's non-domiciled CDL final rule took effect 16 March 2026 and is removing roughly 194,000 drivers (about 200k holders down to roughly 6k), with California revoking around 17,000 CDLs and New York facing 16,000+ — so brokers are vetting harder against a shrinking, churning carrier base. By 2029-2031, negligent-selection verdicts will have repriced broker liability insurance and provable carrier quality becomes the gating asset in a $1T+ freight market. | J34: Every dollar in this category went to the buyer of vetting — brokers and 3PLs — because that is who has budget and who ate the fraud losses. Carrier-side pain was previously merely annoying, so no product exists whose customer is the carrier; SCOTUS made it existential and the market has had under three months to react. The magnitude is measured: Overdrive's 2026 owner-operator survey found only 39% of owner-operators had never been denied business based on information in a vetting platform — meaning 61% have been — with RMIS at 69% and Highway at 61% penetration. | K34: Start as a service, not software. A two-person shop charges owner-operators $99/month to monitor their FMCSA/SAFER/CSA profile, insurance certificates and status across the vetting platforms, alerts them the day something flips, and files corrections and DataQs on their behalf. Distribution is free and immediate: X, TikTok and trucking podcasts where these operators already rant about Highway and RMIS daily. Ninety-day target: 1,000 paying carriers plus the denial-cause dataset, which is what you later sell back to brokers as defensible-selection evidence. | L34: X / Twitter builder, operator and investor discourse | M34: https://x.com/lets_truck/status/2054979133667790970 https://x.com/gop_is_gutless/status/2055603125281546718 https://x.com/FreightWaves/status/2054940324301013056 https://x.com/FreightWaves/status/2057788981236875414 https://x.com/BLaw/status/2054944839779631494 https://x.com/ShopFloorNAM/status/2080781974680002925 https://www.dlapiper.com/en-us/insights/publications/2026/05/supreme-court-rules-freight-brokers-can-be-held-liable-under-state-negligence-law https://www.overdriveonline.com/business/article/15684513/new-carrier-vetting-craze-among-brokers-bad-for-trucking https://www.jacksonlewis.com/insights/fmcsa-new-rule-cracks-down-non-citizen-commercial-drivers-licenses-creating-carrier-burdens
A35: condo-project-eligibility-remediation | B35: Condo project remediation for the GSE mortgage-ineligible list | C35: No | E35: Search-backed | F35: =IFERROR(INDEX('Screening Scores'!$I:$I,MATCH($A35,'Screening Scores'!$A:$A,0)),"") | G35: cut | H35: Fannie Mae and Freddie Mac maintain non-public lists of condo and co-op projects ineligible for conventional financing; a project lands there for deferred maintenance, structural findings, thin reserves or non-conforming insurance, and the first anyone learns of it is when a buyer's loan dies at underwriting. Build the diagnostic-and-remediation business: assess a project against published GSE eligibility criteria, produce the specific defect list, run the fixes (reserve study, insurance rebuild, structural documentation, assessment plan), and maintain a continuously updated project eligibility file that lenders and listing agents can trust. The recurring revenue is a per-project subscription sold across a management company's whole portfolio; the second line is selling verified project status to lenders and agents. | I35: Honest caveat: the group's raw material contains no single published effective date for the decisive unlock. The dated and numeric facts that do exist are the June 2021 Surfside collapse that drove the criteria tightening, 696 ineligible projects reported across three South Florida counties as of March, and a reported figure of up to ~1,700 projects nationally. The reported 2026 catalyst — Fannie Mae and Freddie Mac moving to add transparency to the condo lending lists — is sourced only to press coverage with no effective date attached, and must be verified before it is treated as a trigger. What is structurally certain is that aging 1970s-80s condo stock, spiking insurance costs and the spread of state structural-integrity and reserve-study mandates outward from Florida grow the affected population every year through 2031. | J35: Proptech capital went to brokerage, rentals and mortgage origination. Association governance is served by decades-old HOA software (Yardi, AppFolio, TOPS) that handles accounting and violations, not capital-markets eligibility. Property managers, boards and lenders each assume one of the others owns the problem, so nobody does. The opacity is the whole mechanism: because the list is secret there is no market signal, no ranking and therefore no product — which is exactly the arbitrage. Reported scale is 696 affected projects across Miami-Dade, Broward and Palm Beach as of March, and figures up to roughly 1,700 projects nationally, but the true number is unknown because the list is hidden. | K35: 90 days: encode the published Fannie/Freddie condo project standards — insurance limits and deductibles, the 10% reserve contribution, deferred maintenance, special assessments, litigation, investor concentration — into a one-hour self-assessment a board member or manager can complete, producing a scored defect report with dollar-ranged remediation estimates. Do not charge for the assessment; charge for remediation delivery (reserve studies, insurance broker placement, structural engineering coordination) and for a standing project eligibility file. First customer is a regional property management company with 40-80 associations under management in South Florida, sold as portfolio triage before their next renewal season. | L35: Reddit / unglamorous-trades practitioner lens, run WITHOUT working fetch. METHOD CAVEAT: the scout's egress gateway returned HTTP 403 on CONNECT for every host attempted, so WebFetch was unusable and WebSearch refuses reddit.com outright; no verbatim practitioner quotes could be captured, and signal_quotes were deliberately omitted rather than fabricated. Every URL is real and surfaced by WebSearch, but evidence is SEARCH-LEVEL, NOT PRIMARY-VERIFIED — the GSE transparency claim in particular needs primary confirmation. Substitute method: dated regulatory triggers, sunset notices and agency rulemakings reachable by search. | M35: https://www.ksnlaw.com/blog/condo-hoa-unavailable-list/ https://themortgagereports.com/118206/is-your-condo-on-fannie-maes-blacklist https://newenglandcondo.com/article/fannie-maes-secret-blacklist-of-properties-2 https://www.aol.com/fannie-mae-freddie-mac-add-103000226.html https://riseamg.com/fannie-mae-blacklisted-condos/ https://www.aol.com/florida-condo-secret-blacklist-blocking-093000496.html
A36: congregation-space-third-place-operator | B36: Master-Lease Operator for Empty Congregation Space | C36: No | E36: Search-backed | F36: =IFERROR(INDEX('Screening Scores'!$I:$I,MATCH($A36,'Screening Scores'!$A:$A,0)),"") | G36: cut | H36: US congregations hold the largest stock of already-built, already-permitted community space in the country — fellowship halls, commercial kitchens, gyms, childcare-licensed rooms — sitting idle roughly six days a week, in buildings whose congregations are shrinking but not closing. The business is not buying these buildings; it is operating them. Sign standardized master use agreements with 10-30 congregations in a single metro, take over insurance, keys, scheduling, cleaning and licensing, and fill weekday hours with paying programs: licensed childcare and after-school, senior day programs, supper clubs, coworking. Revenue share with the congregation, gross margin on the programming, and a portfolio of space that no single operator could assemble on the open market. | I36: The one firmly dated trigger in the raw material is California SB 4 (2023), the YIGBY statute that made faith-owned land legally and politically legible, plus copycat bills in other states — which pushed congregational boards into commercially framing their footprint for the first time. Beyond that, be plain: the supporting claims are unverified. The scout flagged the 'Pew 2025 religious affiliation plateau' explicitly as [unverified], and the claim that municipal social-infrastructure/loneliness funding has become a budget line item is asserted with no dated source. There is no verified numeric trigger here — no measured vacancy rate, no dated funding program. Verify SB 4's effective date and copycat-state adoption count before capitalizing anything on this. | J36: The conversation about faith real estate is polarized into two poles that both skip the middle. One pole treats congregational decline as a culture story with no commercial implication. The other pole is adaptive reuse into housing under the 'Yes In God's Backyard' laws — a slow, capital-intensive developer game requiring entitlement, financing and years. The light-capital OPERATING layer between them has no branded player: congregations rent ad hoc to whoever calls, at below-market rates, with no standard agreement, no insurance wrapper and no sales function. Meanwhile the well-capitalized loneliness and third-place startups are building matching apps and dinner clubs with no space of their own — they are demand for this business, not competition. Note: the scout that surfaced this had zero live web verification, so 'nobody is doing this in a US metro' is an untested hypothesis and is explicitly the first thing to check. | K36: Two founders, one metro, zero code. Days 1-30: retain a broker to build a liability/COI wrapper that lets a third party program someone else's sanctuary building, and draft one 3-page master use agreement with a 70/30 revenue split. Days 30-60: sign five congregations, selecting only for buildings that already hold a childcare-licensed room or a commercial kitchen — those two assets carry the permits that take everyone else 18 months to get. Days 60-90: do not invent your own programming first. Sublet weekday hours to operators who are already turning customers away for lack of licensed space — a childcare center with a waitlist, a senior day program, a caterer needing commissary hours. They are the first customer and they pay on day one. Own-brand programming (after-school phone-free clubs, supper clubs) comes in quarter two once the space portfolio and insurance stack are proven. | L36: Consumer behavior, culture, and status shifts with commercial consequences | M36: https://www.pewresearch.org/religion/ https://leginfo.legislature.ca.gov https://www.partnersforsacredplaces.org
A37: contractor-license-qualifier-succession | B37: Qualifying-Party Succession: Keeping Trades Roll-Ups Legally Able to Pull Permits | C37: No | E37: Search-backed | F37: =IFERROR(INDEX('Screening Scores'!$I:$I,MATCH($A37,'Screening Scores'!$A:$A,0)),"") | G37: cut | H37: In most US states a contracting business can only pull permits under a named individual license holder — California's RMO/RME, Florida's qualifier, the master electrician or plumber of record. That person is usually the retiring founder, and when they leave the entity legally stops being able to work regardless of who owns the equity. Build the qualifier-succession system: a jurisdiction-by-jurisdiction rules engine for which entity/license/qualifier combinations are valid, apprentice-hour capture to manufacture replacement qualifiers in-house, and multi-state license-portfolio management for acquirers. The analogue that proves the category works is insurance producer licensing, already a mature software market. | I37: Partial trigger only, and the group's raw material is honest about the gap. The one dated figure that survives is demographic: roughly 51% of privately held US business owners are 55+ as of 2026, and the qualifying party is disproportionately drawn from exactly that founder cohort. The supporting claim — that PE-backed HVAC/plumbing/electrical/roofing platforms are acquiring across state lines at record pace, multiplying jurisdiction-qualifier pairs per buyer — has no dated or numeric source in the raw material and should be treated as a hypothesis to verify against deal-count data before this is funded. There is no known effective date or regulatory change driving the timing. | J37: Home-services software capital is pointed almost entirely at CRM, dispatch, and now AI call answering — the revenue-facing layer. The binding legal constraint on trades M&A is not price or software but who holds the license the day after close, and that is handled today by email threads, a compliance clerk, and legally grey license-rental arrangements that states actively prosecute. The scout found no purpose-built product here, but flags this specific claim as unverified: no competitive scan was possible in-session because web egress was blocked, so a 2-day competitor sweep is the first thing to do before writing code. | K37: Pick five states with the nastiest qualifier rules — CA, FL, NV, AZ, NC — and build the authoritative rules engine plus a qualifier renewal and continuity calendar for just those. Sell it first as a diligence product to PE-backed trades roll-ups and restoration nationals, framed as a single question: will this deal survive the seller's retirement? Distribution is through deal lawyers and trades-focused search funds, not marketing. Two people, four months; apprentice-hour tracking that produces the next qualifier is phase two, once the diligence product has proved the buyer exists. | L37: Demographic and labor-supply shifts that are mathematically certain and commercially ignored | M37: https://www.bls.gov/news.release/ecopro.nr0.htm https://www.forbes.com/sites/josephcoughlin/2026/05/05/the-clock-no-one-set-americas-small-business-succession-crisis/ https://www.foxbusiness.com/small-business/millions-jobs-vulnerable-silver-tsunami-looms-us-small-businesses-experts-warn
A38: customs-bond-sufficiency-mga | B38: Customs bond sufficiency radar for tariff-exposed importers | C38: No | E38: Search-backed | F38: =IFERROR(INDEX('Screening Scores'!$I:$I,MATCH($A38,'Screening Scores'!$A:$A,0)),"") | G38: cut | H38: A continuous customs bond is sized at 10% of the importer's prior-year duties, taxes and fees, so when tariff rates jump 3-5x the bond silently goes insufficient and CBP halts cargo at the port with a surprise insufficiency notice. Build the monitoring layer first: pull an importer's ACE/ABI entry summary data, forecast rolling 12-month duty liability, project the exact date the bond goes short, and broker the increase before CBP notices. Revenue starts as a per-importer SaaS subscription plus surety agency commission on every bond increase you trigger, and graduates into an MGA writing the customs surety itself once you can prove a loss-ratio edge from having real-time duty exposure data no surety has today. | I38: CBP recorded 27,479 bond insufficiencies in fiscal 2025 worth nearly $3.6 billion — the highest count and highest total value ever recorded, roughly double the 2019 Section 301 peak, and CNBC put the shortfall at $3.5 billion in a Feb 12, 2026 report. 2026 stacked new layers on top: a 10% universal Section 122 surcharge effective Feb 24, 2026; restructured Section 232 steel and aluminum duties at 50% of full customs value effective April 6, 2026; and indefinite suspension of the de minimis exemption by regulation effective June 24, 2026, with statutory repeal following July 1, 2027. Bond amounts now span the $50,000 minimum to $450 million, and duty levels look like a durable feature of the 2026-2031 political economy, so exposure recomputes and compounds every year. | J38: This sits in the seam between customs brokers, who do not underwrite, and sureties, who do not build software — so neither builds the product. The entire trade-tech funding wave went to HTS classification, landed-cost calculators and duty drawback (drawback alone drew roughly half a dozen funded 2026 entrants); bond adequacy drew none. Sureties are reportedly managing 200-550% bond increases on spreadsheets, and CBP surfaces insufficiency as an after-the-fact notice rather than a forecast, so the importer's first signal is cargo already stopped. | K38: Two people — one licensed customs broker, one engineer. Months 1-2: build the ACE/ABI data pull plus a rolling duty-forecast model, and sell a $500/month bond sufficiency monitor to 50 mid-market importers using customs brokers as the referral channel (brokers want the save, not the liability). Month 3: sign on as an agent of one existing customs surety and take commission on every bond increase the monitor triggers. No balance sheet or capital required for phase one; the MGA only comes after the forecast data proves out. | L38: X / Twitter builder, operator and investor discourse, harvested via site:x.com search (direct WebFetch to x.com and most primary sites was blocked by proxy policy) and cross-validated against dated primary sources: Federal Register notices, SCOTUS opinions, EU directives, CBP data, FMCSA rules, ISO form filings and industry lead-time indices. Bias toward operators (freight brokers, importers, data center developers, hardware manufacturers) over commentators, and toward dated 2026-2028 regulatory triggers the AI-startup crowd is not looking at. | M38: https://sourcingjournal.com/topics/trade/cbp-customs-bond-insufficiencies-importers-tariffs-1234813629/ https://www.cnbc.com/2026/02/12/trump-tariffs-us-customs-record-bond-funding-issues-flagged.html https://www.cnbc.com/2026/02/06/supreme-court-trump-tariffs-case-decision-refunds-customs-bonds.html https://suretyone.com/blog/customs-bond-sufficiency-amid-rising-tariffs-implications-for-customs-sureties/ https://www.federalregister.gov/documents/2026/06/24/2026-12670/indefinite-suspension-of-the-de-minimis-exemption-for-merchandise-arriving-through-all-modes-other https://capwolf.com/u-s-customs-bond-shortfall-hits-record-3-6-billion-amid-tariffs/
... A78: supervised-hours-marketplace | B78: Board-Compliant Supervised-Hours Marketplace for Behavioral Health Licensure | C78: No | E78: Search-backed | F78: =IFERROR(INDEX('Screening Scores'!$I:$I,MATCH($A78,'Screening Scores'!$A:$A,0)),"") | G78: cut | H78: Dozens of licenses cannot be minted without documented supervised hours signed by an approved senior — LCSW/LPC/LMFT, psychologists, real estate appraisers, architects on AXP, land surveyors, CPAs. Two forces squeeze this at once: the supervisor cohort is retiring, and AI is absorbing the junior task volume that used to generate the billable hours a trainee logged. Build the supervision marketplace: hour attestation and audit trails that match each state board's exact forms, supervisor liability insurance, structured competency sign-off, and paid supervision as a genuine two-sided market. The statutory hour requirement is the choke point, which is what gives this a payer rather than an audience. | I78: Dated/numeric trigger present in the BLS 2024-2034 Employment Projections: office and administrative support is projected to shed 696,300 jobs (-3.5%), with six of the top-20 occupational declines being administrative roles — cashiers -313,600, office assistants -177,800, bookkeepers -94,300, payroll clerks -27,000, sales -290,000, production -11%. That is the same junior-task substrate that fed several credential ladders. The supervisor retirement wave is concurrent rather than forecast. One claim needs verification before launch: that appraisal and other boards have already authorized simulation or practicum alternatives to human apprenticeship — that regulatory door is the unlock, and its current status was not confirmed in-session. | J78: The 'AI eats entry-level white collar' discourse is loud and entirely descriptive — it generates think-pieces, not products, because nobody has traced it to a consequence with a legal requirement attached. The licensure consequence is that consequence: when junior task volume collapses, the hours cannot be logged, the license cannot be minted, and the profession's supply curve breaks. No incumbent connects hour-logging, supervisor recruitment, and board-form compliance into one product; today it is PDFs, spreadsheets, and a supervisor doing an unpaid favor. | K78: Pick exactly one credential with a documented shortage and a permissive board — LCSW/LPC behavioral health licensure is the highest-volume candidate because employers are desperate enough to pay for supervision as a recruiting benefit. Build hour-logging that reproduces that single state board's exact form, field by field, so a supervisee's export is filing-ready. Recruit 30 retired-but-still-licensed supervisors as the supply side and charge employers per supervisee per month. First customer is a community mental health agency or a mid-size group practice with open clinician reqs. The state-by-state board rules engine, accumulated one state at a time, is the moat. | L78: Demographic and labor-supply shifts that are mathematically certain and commercially ignored | M78: https://www.bls.gov/news.release/ecopro.nr0.htm https://www.visualcapitalist.com/us-jobs-losing-most-workers-by-2034-ranked/ https://iawponline.org/news/what-the-new-bls-long-term-job-projections-mean-for-workforce-development/

Sheet Screening Scores
A1: ID | B1: Opportunity | C1: Evidence | D1: Overlooked | E1: Inflection | F1: Buildable | G1: Market | H1: Defensibility | I1: Composite | J1: Verdict | K1: Competitor check (what the searches found) | L1: What kills it
A2: grid-equipment-slot-forward-exchange | B2: Forward exchange for transformer and switchgear production slots | C2: Search-backed | D2: 7 | E2: 7 | F2: 7 | G2: 7 | H2: 6 | I2: =ROUND(D2*Overview!$B$24+E2*Overview!$B$25+F2*Overview!$B$26+G2*Overview!$B$27+H2*Overview!$B$28,2) | J2: advance | K2: The adjacent PHYSICAL secondary market is crowded, but forward SLOT trading appears genuinely empty. Confirmed physical-equipment competitors: Anza Exchange (exchange.anzarenewables.com — explicitly a B2B marketplace to buy/sell NEW power transformers and HV breakers, plus a separate Anza transformer procurement service), Transformer Exchange Inc, Utility Surplus Exchange, Electrical Trader, Surplus Record, MegaGrid Supply, Mission Critical Facilities International, CIRKLA. Advisory/data adjacents: Build.inc (2026 transformer procurement insights), Terrapin Consulting lead-time index, GridReadiness, POWER Magazine remanufacture/build-to-stock coverage. Repeated searches for a venue trading undelivered order slots, capacity reservations or deposit assignments in grid iron returned nothing — every 'capacity reservation secondary market' hit was GPU/cloud compute (Compute Exchange, AWS RI resale, BigQuery slots), not electrical equipment. Nasdaq's power derivatives are energy, not equipment. Also verified: 'Capacity allocation occurs through prepayments, where buyers wire money upfront to hold a slot in the queue' (chargeduppro/Build.inc) and OEMs are booked 3-4 years out (GE Vernova, Hitachi Energy, Mitsubishi Electric), so the underlying asset is real. why_now checks out precisely: FERC issued FPA §206 show cause orders to all six RTOs/ISOs on 18 June 2026 in the RM26-4 proceeding, defining large loads as >50MW on >69kV lines, with 60-day responses due 17 Aug 2026 (McGuireWoods, Bracewell, Baker Botts, White & Case, Day Pitney, Troutman all confirm). Lead times verified: LPT averaging 128 weeks, GSU 144 weeks, up to 4 years in constrained segments (pv-magazine USA, 11 May 2026). | L2: The whole business runs through the OEM's consent. Standard supply agreements carry anti-assignment/anti-delegation clauses and non-refundable staged deposits; once an OEM learns a slot is worth more than the contract price it has every incentive to cancel, keep the deposit and re-sell at market itself rather than let a broker capture the spread. Warranty assignability is separately restricted. Second risk: the phantom-demand premise is contested — SemiAnalysis published 'Stop Saying Half of 2026 US Datacenter Capacity Is Canceled' rebutting exactly the cancellation statistic this thesis rests on, and if hyperscaler demand holds, orphaned slots never accumulate and there is nothing to clear. Third: Anza already runs a new-equipment exchange plus a procurement desk and is one product decision away from listing undelivered slots. Evidence quality is also weak — six of the ten cited URLs are x.com posts.
A3: invoice-xml-ingestion-firewall | B3: Ingestion firewall for government-cleared e-invoices (hostile XML on national tax rails) | C3: Search-backed | D3: 7 | E3: 6 | F3: 8 | G3: 5 | H3: 5 | I3: =ROUND(D3*Overview!$B$24+E3*Overview!$B$25+F3*Overview!$B$26+G3*Overview!$B$27+H3*Overview!$B$28,2) | J3: advance | K3: The space is populated by CONFORMANCE validators, not adversarial ones — a real distinction. Found: easybill/e-invoice-validator (open source, Peppol BIS / XRechnung / Factur-X / EN16931 schematron), ecosio free validator, Invoice Navigator (explicitly supports KSeF), B2BRouter, Sorgera (Peppol + KSeF), MyInvoice, eaglessoft. Every one validates schema/schematron conformance; none markets injection quarantine, homoglyph/bidi detection, entity-expansion limits or a hold-and-release console. Compliance incumbents (Sovos, Avalara E-Invoicing and Live Reporting, ONESOURCE Pagero, Tradeshift, EDICOM) sell transmission, legal validity and AP receipt — searches surfaced zero receive-side security features from any of them. One security researcher occupies the topic (invoice.secvuln.info, 'Security Issues with Electronic Invoices and EU eInvoicing'), with a documented ZUGFeRD XXE that exfiltrates server files, and notes Java stdlib and Saxon ship insecure defaults inside the e-invoicing ecosystem — corroborating the threat while confirming no vendor owns it. Real overlap to respect: the generic capability is a 20-year-old product category — IBM DataPower XML Firewall (schema validation, threat protection, entity limits, still documented at v10.6.0) and Forum Sentry XML Gateway do this class of filtering already, just without country schema packs. | L3: Two live risks. (1) A security-first framing may not have a budget owner: there is still no confirmed public incident of an ERP compromised via a cleared e-invoice, so the 'first breach makes this board-level' step is a hypothesis, and until it happens the buyer may treat it as an XML-gateway config problem they already own via DataPower/Saxon hardening. (2) Sovos or Pagero can bolt receive-side sanitization onto an existing KSeF/Peppol pipeline once it becomes a checkbox, and they already hold the receiving-entity relationship. Market size is the real ceiling — realistic buyers are ERP vendors, ASPs and mid-market receivers per country, not a multi-billion pool. The why_now, by contrast, is the strongest in this batch and verified: KSeF is mandatory 1 Feb 2026 for taxpayers over PLN 200M, 1 Apr 2026 for all other established taxpayers, Jan 2027 for micro-entrepreneurs, the Ministry of Finance has stated deadlines will NOT be postponed, and the clearance model is confirmed (an invoice has no legal existence until KSeF accepts it) — so the receive-side cohort is arriving on schedule right now.
A4: cui-determination-for-machine-shops | B4: CUI determination and marking for small defense machine shops | C4: Search-backed | D4: 6 | E4: 7 | F4: 7 | G4: 5 | H4: 4 | I4: =ROUND(D4*Overview!$B$24+E4*Overview!$B$25+F4*Overview!$B$26+G4*Overview!$B$27+H4*Overview!$B$28,2) | J4: advance | K4: Exact wedge (parse DoD distribution statements B-F / DFARS 7012 flow-down / export-control markings out of PDFs and CAD title blocks, emit a written CUI-vs-FCI determination + marking overlay + shop-floor label) was NOT found as a product across four differently-worded searches. But the surrounding lanes are dense. Generic data classification that explicitly claims CUI: Fortra/Titus Data Classification Suite, Microsoft Purview (the default for GCC/GCC High shops, per Summit 7 and Cleared Systems), Secuvy (press-released AI CUI categorization for CMMC in 2025), Actifile, BigID. CMMC compliance software/advisory: Totem Tech (claims 1,000+ small DIB manufacturers, publishes the leading DoD CUI Identification Guide), PreVeil, Summit 7, CyberSheath, ControlCase, Copla's '7 CMMC platforms' roundup. Most dangerous: the incumbents already inside the machine shop's document workflow — ProShop ERP publishes '3 Tips to Manage CUI in a Machine Shop', is ITAR-compliant and already generates the digital traveler packet; Paperless Parts is CMMC-compliant + FedRAMP Moderate Equivalent + 3PAO-audited for quoting in exactly this vertical. Both could bolt determination onto an existing install base. On the channel side, the intended reseller already monetizes this manually as a named SKU: InitCyber sells a fixed-fee 'CUI Data Flow & Scoping Workshop', Techvera runs 'CUI scoping exercises', CyberSheath and ControlCase both market scoping. Verdict on crowding: no direct competitor, but the buyer's wallet is contested from three directions. | L4: why_now verified and holds: 48 CFR CMMC final rule published in the Federal Register 10 Sep 2025, Phase 1 effective 10 Nov 2025, DFARS 252.204-7021 now in new solicitations, Phase 2 third-party Level 2 ramp from ~Nov 2026. Real risks are commercial, not factual. (1) Channel conflict: CUI scoping is the most-billed hour in a consultancy's engagement — a tool that automates it cannibalizes the reseller's own revenue, so 'they will resell it' is the weakest link in the thesis. (2) Liability: a shop will not accept an automated CUI determination without a human attestation, so the product degrades into a workpaper generator with consultant sign-off, compressing price. (3) One-time purchase shape — scoping happens at engagement start, not monthly, so recurring revenue is unproven. (4) Microsoft Purview is already paid-for in every GCC High seat and is the path of least resistance for the MSP channel. (5) Small ACV against a long tail of 30-person shops facing $20k-$100k total compliance cost, most of which goes to the enclave, not to determination.
A5: small-business-wind-down-desk | B5: Wind-Down Desk: Asset Re-Homing for the Small Businesses That Never Sell | C5: Search-backed | D5: 6 | E5: 7 | F5: 8 | G5: 4 | H5: 3 | I5: =ROUND(D5*Overview!$B$24+E5*Overview!$B$25+F5*Overview!$B$26+G5*Overview!$B$27+H5*Overview!$B$28,2) | J5: advance | K5: Adjacent lanes are well funded but all aim elsewhere; the specific motion — harvesting business brokers' rejected and expired listings and re-homing the customer book, license/permit, crew and equipment for a success fee — was not found in any search. Nearest funded players and why they miss: SimpleClosure ($20M+ total, $15M Series A May 2025 led by TTV, plus Carta/Anthemis/LegalTech Fund) automates dissolution paperwork and investor distributions for venture-backed startups, not Main Street asset re-homing. Teamshares ($245M raised, 85+ businesses in 30+ states, $490M consolidated revenue) explicitly markets against '70% of small businesses lack buyers' but only acquires businesses that are profitable and sellable — it is the direct competitor for the good listings and a non-competitor for the reject pile. Common Trust ($2.6M seed, Crossbeam/Schmidt Futures) and Project Equity do employee-ownership buyouts, again for viable companies. Restructuring/wind-down firms J.S. Held, Ravix Group, Arkus Advisory, VLPC, Bizcap, Aevitium, Cornerstone Licensing all serve distressed mid-market at $6.5k-13k+ managed-wind-down pricing, not micro-business value recovery. Book-of-business brokerage is mature but only in high-value verticals (insurance agencies, dental, accounting, routes) via BizBuySell, Sunbelt, Benchmark, BayState, with Live Oak Bank financing purchases. Business-broker economics genuinely do exclude the reject pile, and no one found is farming it. | L5: why_now is the best-verified in this batch: McKinsey Institute for Economic Mobility (Feb 2026, covered by Forbes/HousingWire/ATR) puts 6M US SMBs into ownership transfer by 2035 with ~1M sold at ~$5T cumulative, >50% of owners already 55+, ~92% of exits ending in closure rather than sale, ~5% of exiting owners completing a sale, and annual exits up to 42% above 2011 levels (~665k/yr) by 2035. The candidate's ~30% and 6.46% close-rate figures are shakier secondary snippets, but the McKinsey spine holds without them. Real risks are economic, not factual. (1) Unit economics: a business with no buyer has near-zero recoverable value by definition — a success fee on a $50-150k customer book is $5-15k, against weeks of bespoke legal, licensing and placement labor, so gross margin per engagement is thin and the sales cycle is emotionally loaded with a distressed, often unresponsive owner. (2) Zero defensibility: broker referral relationships are the only asset, they are per-metro, non-exclusive and replicable, and there is no compounding data — the candidate's own plan defers software until after 10 manual engagements. (3) Supply risk: brokers may not hand over reject lists at all, since a dead listing is still a relationship they may want to re-approach, and privacy/engagement-agreement terms complicate transfer. (4) Ceiling: this is a regional professional-services firm, not a venture-scale outcome, and the 6M/$5T TAM narrative wildly overstates the monetizable slice. Advancing on wedge honesty and buildability, not on size.
A6: biosolids-outlet-exchange | B6: PFAS-Compliant Biosolids Outlet Exchange for the Mid-Atlantic | C6: Search-backed | D6: 5 | E6: 7 | F6: 8 | G6: 5 | H6: 4 | I6: =ROUND(D6*Overview!$B$24+E6*Overview!$B$25+F6*Overview!$B$26+G6*Overview!$B$27+H6*Overview!$B$28,2) | J6: advance | K6: No dedicated biosolids outlet exchange, capacity marketplace, or cross-state PFAS-threshold arbitrage broker found across four query framings — that shape genuinely looks unbuilt. BUT the customer is already served by large full-service incumbents delivering the identical outcome (firm per-ton price, compliant destination, documentation): Synagro (largest US biosolids manager, publicly investing in PFAS destruction tech), Denali Water Solutions (PE-backed; the two swapped asset portfolios in Aug 2024), Merrell Bros., US Submergent, Agri-Sludge, Midwest Injection, plus Casella/WM/Veolia on landfill and thermal. Johnson County KS just awarded Denali a 3-year land-application contract at ~$1M/yr with commissioners raising PFAS concerns — i.e. procurement already runs through incumbents. Source-control/pretreatment consulting is covered by Brown and Caldwell, Hazen, CDM Smith, EA Engineering; Bluefield Research covers the market analytically. why_now VERIFIED PRECISELY: Maryland SB 719 signed 28 April 2026, bans land application at or above 50 ppb PFOA/PFOS from 1 October 2028, with a 25-50 ppb restricted tier and a mandatory source-identification/mitigation duty above 25 ppb — the strongest-verified trigger in this batch. Maine/Connecticut bans and EPA's 2026 biosolids PFOA/PFOS draft guidance also corroborate. | L6: Defensibility is the weak leg: non-exclusive outlet contracts, zero capex, and no proprietary data mean Synagro or Denali can match any quoted per-wet-ton price and bundle the hauling you do not own. The 'knowing which outlet accepts which concentration this quarter' edge is a decaying asset — once state thresholds stabilize (MD's are already written into statute with numbers), the arbitrage compresses. Landfill airspace is the substitution risk in the other direction: Maryland/Maine reporting already flags landfill capacity concerns, so the outlets you forward-contract may themselves be closed to biosolids by state action. Market size is modest — US biosolids management is single-digit billions of total spend and a Mid-Atlantic broker's take rate is a thin slice of that. Working capital risk if you sign firm per-ton prices against outlet costs that reprice.
A7: azole-resistance-hotspot-control | B7: Azole-resistance hotspot mapping and compost protocol certification for green-waste operators | C7: Search-backed | D7: 8 | E7: 4 | F7: 8 | G7: 3 | H7: 5 | I7: =ROUND(D7*Overview!$B$24+E7*Overview!$B$25+F7*Overview!$B$26+G7*Overview!$B$27+H7*Overview!$B$28,2) | J7: borderline | K7: This one genuinely looks empty on the commercial side and the 'zero commercial actors' claim largely survives scrutiny. Everything I found is academic or public-sector: the FUNgalSnelders lab at Wageningen (studies environmental-to-clinical azole resistance transmission and airborne exposure quantification), Radboudumc-CWZ Center of Expertise for Mycology with RIVM Bilthoven, Statens Serum Institut's Mycology Reference Laboratory in Denmark, published environmental hotspot surveys from Belgium (two composting facilities plus horticulture, six pan-azole-resistant isolates), Ohio, Georgia USA (TR46 in 30% of samples incl. compost, hibiscus, hemp), and the Netherlands. The only commercial artifact is VIPcheck, an azole-screening agar plate — a consumable, not a surveillance or certification service. Public programmes are moving into the space and would be the real competitors for any tender: the UK PATH-SAFE programme covers antifungal-resistance molecular epidemiology, DHSC put £12M over five years into fungal research, WHO published a GLASS-FUNGI blueprint on 30 June 2026 (though scoped to Candida bloodstream infections, not environmental), the Fungal One Health AMR Network launched 24 Apr 2025, and the Botucatu Document (Dec 2025) calls for environmental aerobiome surveillance. On the certification side, PAS 100 / the Compost Certification Scheme (audited by bodies like Aardvark) is the incumbent framework a resistance module would have to plug into or displace. why_now verified: the EFSA/ECDC/ECHA/EEA/EMA joint opinion (10.2903/j.efsa.2025.9200) is real, names stockpiled agricultural waste, soil amendment use and freshly cut wood as resistance-selection hotspots, and recommends 'proper agricultural and wood waste storage and management.' | L7: There is no buyer and no deadline. The candidate honestly concedes the EFSA output is a recommendation with no effective date, and the 2028-2031 mandatory-management window is pure extrapolation — EU scientific opinions frequently produce nothing binding for a decade or never. Meanwhile the paying customer is structurally absent: green-waste composters and bulb cooperatives run on thin margins and have no liability exposure for a hospital infection three towns away, and hospitals buy infection control inside their own walls, not catchment epidemiology from a private lab. The founding move (publish the national hotspot map, then sell to everyone on it) is antagonistic — you name operators as public health hazards and then invoice them, which is a hard first sale and invites the trade association to fund a rebuttal instead. Publishing the map also destroys the information asymmetry and hands the method to Wageningen, SSI or a national agency who can run it for free with better credibility. Realistic ceiling is a single-country consultancy of a few million euros, not a venture outcome.
A8: funded-claim-detection-for-casualty | B8: Funded-Claim Detection for Casualty Reserving | C8: Search-backed | D8: 6 | E8: 6 | F8: 6 | G8: 5 | H8: 6 | I8: =ROUND(D8*Overview!$B$24+E8*Overview!$B$25+F8*Overview!$B$26+G8*Overview!$B$27+H8*Overview!$B$28,2) | J8: advance | K8: Adjacent space is busy but the specific wedge (resolving funder beneficial ownership through state registries and linking it to individual open claims) is not productized by anyone I could find. Real adjacent players: Verisk runs a full TPLF content program (legislative activity map, Jan 2026 transparency insight, 2021 webinar 'Who's Funding the Case?') but sells no claim-level funder-detection product; Findevor launched an AI 'legal system abuse prevention' product for casualty insurers that cross-references plaintiff-firm activity and judicial hotspot maps — closest overlap; CLARA Analytics (CLARA Litigation) predicts attorney involvement and litigation propensity with plaintiff/defense attorney scorecards; Gen Re publishes casualty litigation analytics guidance; Premonition, UniCourt, LexisNexis CourtLink and Docket Alarm supply the docket substrate anyone would build on; Westfleet Advisors publishes the annual funder market report (39 funders identified) but at market level, not claim level; NICB has called for transparency without building a tool. why_now verified and holds: Georgia SB 69 signed 21 Apr 2025 with NMLS litigation-financier registration effective 1 Jan 2026 ($25k threshold, $2,000 fee); S.3826 Litigation Funding Transparency Act of 2026 confirmed introduced by Grassley on 11 Feb 2026 with Tillis, Kennedy, Cornyn, covering class actions/MDL/100+ case aggregations; EY's ~$50B-over-five-years / 4-5.2% loss-ratio-drag figure confirmed in trade press. The Law.com 17 Jul 2026 open-records piece on Georgia's registry is real, supporting the claim that no commercial provider had assembled the list. | L8: The thesis is self-cannibalizing. The same disclosure wave that creates the raw material also destroys the need for detection — Georgia, Kansas, Indiana, Louisiana, Montana, West Virginia and Wisconsin already mandate funder-identity disclosure, ISO has approved a Litigation Funding Disclosure Condition endorsement, and S.3826 would federalize it for class actions and MDLs. If disclosure becomes routine by 2028-2029, insurers get funder identity for free and a paid inference product is worth little. Second, the data-linkage claim is weaker than stated: consumer pre-settlement advances to individual plaintiffs are generally not UCC-1 filed (UCC-1s attach to businesses and law-firm portfolio deals), so the 'cross-join UCC-1 to open claims' mechanic likely resolves only firm-level portfolio funding, not per-claim funding at FNOL. Georgia's registry lists funders and their owners, not which cases they funded — the case linkage is the hard, unsolved part and the 90-day plan quietly assumes it. Third, Verisk or Findevor can bolt this on as a feature the moment it looks valuable; neither lacks the docket data or the carrier relationships.
A9: in-person-practical-assessment-days | B9: In-Person Work-Sample Assessment Days for One Role Family | C9: Search-backed | D9: 5 | E9: 6 | F9: 8 | G9: 5 | H9: 4 | I9: =ROUND(D9*Overview!$B$24+E9*Overview!$B$25+F9*Overview!$B$26+G9*Overview!$B$27+H9*Overview!$B$28,2) | J9: borderline | K9: Both flanks are occupied, but the specific packaging is thin. The assessment-centre category is 40 years old and delivered in person today: SHL TalentCentral is used by the majority of the FTSE 100 and a large share of the Fortune 500 and runs assessment centres, Aon/cut-e runs assessment-centre exercises and is winning switchers (Schroders moved from SHL to Aon), DDI is the third leg, and major employers still end their funnels in person — Deloitte's process terminates in an in-person assessment centre in 2026. Physical proctored seats are commodity infrastructure: Prometric operates 8,000+ locations with in-center and remote delivery, plus Pearson VUE, PSI and Certiport. The anti-cheating layer is its own crowded 2026 startup wave (Humanly integrity layers, Truffle, Karat Qualify, MatchCard, aiseptor). What did NOT turn up in search: an open-market, per-seat, cross-employer service issuing a CANDIDATE-OWNED portable work-sample result for non-licensure role families. That gap looks real; the delivery capability around it does not. | L9: The mechanism is verified better than the candidate claimed — a 2026 sample of 19,368 real interviews showed 38.5% with clear AI-cheating signals, 48% for technical roles, most still passing, and the emerging industry consensus is literally that 'the single most cheat-resistant tool is a work sample.' That is a genuine dated trigger. But the scout's headline number, 'roughly 25 states adopted skills-based hiring policies,' remains UNVERIFIED — my search budget was exhausted before I could count statutes and effective dates, so treat it as unconfirmed. The commercial risks: (1) SHL, Aon and DDI can run this as a line extension on infrastructure and employer relationships they already have, and Prometric can rent them the rooms; (2) candidate-side portable credentials have a brutal historical adoption record — the network effect that turns a services business into a credential is the part most likely to never ignite, leaving a low-margin room-rental operation at $400-600/seat; (3) one role family in one city is a genuinely small starting TAM and metro-by-metro expansion is linear, not compounding.
A10: broker-carrier-credentialing-passport | B10: Carrier-side credential passport after Montgomery v. Caribe | C10: Search-backed | D10: 3 | E10: 8 | F10: 8 | G10: 5 | H10: 4 | I10: =ROUND(D10*Overview!$B$24+E10*Overview!$B$25+F10*Overview!$B$26+G10*Overview!$B$27+H10*Overview!$B$28,2) | J10: cut | K10: Crowded, and crowded specifically by things that shipped in the six months after the ruling. Both halves of the proposed product already exist: (1) carrier-side credential — Highway has already launched a carrier-facing product giving 'carriers the same level of insight that brokers have had for years,' and became exclusive reseller of Bluewire's Broker Package on 7 July 2026; NMFTA's SCAC Verified turned the SCAC into an identity-assured, carrier-paid credential with ID verification required at application/renewal from 26 Feb 2026; Verified Carrier launched Verified Pickup (driver-level verification) in April 2026; Carrier Assure sells carrier-facing performance ratings. (2) The 'defensible-selection evidence package' named as the wedge back to brokers — Descartes shipped AuditLog for MyCarrierPortal on 23 June 2026, and Cipher & Row publishes a 2026 comparison of carrier-vetting audit trails across TMS platforms, Highway and Descartes. The $99/mo monitor-and-file-DataQs service is a mature cottage industry: Foley, Compliance Navigation Specialists, TruckComplianceHQ, FleetCollect, heavyvehicleinspection.com, plus Overdrive's own how-to-win-DataQs guides. Existing vetting incumbents named in the thesis all verify as real and funded: Highway (Dallas, founded 2022, Jordan Graft), RMIS (Transportation API), Descartes MyCarrierPortal, Truckstop Carrier Monitoring, Carrier411. | L10: The dated triggers are the strongest in this batch and both verify exactly — Montgomery v. Caribe Transport II, LLC, No. 24-1238, decided 9-0 on 14 May 2026, holding negligent-hiring claims against brokers fall within the FAAAA safety exception (supremecourt.gov opinion, Justia 608 U.S. ___, Crowell, Gordon Rees, Adams and Reese); FMCSA non-domiciled CDL final rule effective 16 March 2026 with ~194,000 holders affected (FR 2026-02965, 13 Feb 2026; FMCSA FAQ page). The kill is competitive, not factual: the incumbents own the denial-cause dataset by construction — Highway and RMIS see every denial across every broker, a $99/mo aggregator sees only its own subscribers' complaints — so the stated data moat inverts. Distribution is also adversarial: the value depends on brokers honoring a credential issued by a vendor whose explicit pitch is that brokers' vetting is wrong. Revenue base is 600k price-sensitive, high-churn micro-carriers; and the non-domiciled CDL rule shrinks that base rather than growing it. FMCSA's March 2026 proportionate-percentile SMS overhaul also directly reduces the small-carrier score volatility that generates the pain.
A11: superload-route-and-schnabel-brokerage | B11: Pre-Cleared Superload Corridors for Transformers and SMR Modules | C11: Search-backed | D11: 4 | E11: 7 | F11: 6 | G11: 5 | H11: 5 | I11: =ROUND(D11*Overview!$B$24+E11*Overview!$B$25+F11*Overview!$B$26+G11*Overview!$B$27+H11*Overview!$B$28,2) | J11: borderline | K11: Not empty. Permit/routing WITH bridge evaluation is a mature software category: Bentley SUPERLOAD, Hexagon Octave SafeHaul (explicitly bundles 'bridge evaluation'), AASHTOWare PermitRoute powered by ProMiles (used by 57% of states), ProMiles PermitManager, Oversize.io. Permit-service firms (Omni Permits, Beardown, FreightMonster 'Superload & Route Survey Planning') sell multi-state superload orchestration today. Route-survey/transport-engineering with clearance envelopes and axle-load modeling is a standard published service line at Kuehne+Nagel project logistics engineering, Rhenus, AIT, Mammoet (published transformer route case studies), Barnhart, Emmert International, HLI Rail and Rigging (Schnabel service). No pure-play 'pre-cleared corridor certificate' product or Schnabel/HMT slot aggregator surfaced across five differently-worded queries — that specific packaging does look unbuilt. why_now VERIFIED: 128-week power transformer and 144-week GSU lead times confirmed against WoodMac Q2 survey reporting; prices +77%/+45% since 2019; turbine slots tight through 2030. Candidate honestly flags this as numeric-not-regulatory. | L11: The 'pre-cleared route certificate' has no legal standing — states, not you, issue superload permits, and each state re-runs its own bridge analysis, so the certificate sells confidence rather than a binding entitlement. The claimed moat (pre-computed bridge ratings from public state DOT inventories) is built on open data that AASHTOWare Bridge Rating already normalizes for the agencies that actually decide, so Bentley/Hexagon can extend into the shipper side faster than a two-person firm can accumulate corridors. Schnabel option layer is decorative: ~30 cars in North America means the total revenue pool on that asset is trivial and the owners (rail carriers, Emmert, HLI) will not let a broker sit between them and a utility. Requires a licensed PE stamping load ratings, which caps how fast headcount scales and imports professional liability on $12M cargo.
A12: agent-liability-loss-data | B12: The agent-incident loss database that makes agent E&O underwritable | C12: Search-backed | D12: 2 | E12: 8 | F12: 6 | G12: 7 | H12: 5 | I12: =ROUND(D12*Overview!$B$24+E12*Overview!$B$25+F12*Overview!$B$26+G12*Overview!$B$27+H12*Overview!$B$28,2) | J12: cut | K12: Densely occupied on BOTH sides the thesis claims are empty. Acceptance side (the claim was 'no builder at all'): AIUC / Artificial Intelligence Underwriting Company — $15M seed led by Nat Friedman with Anthropic participating, ships AIUC-1 standard + third-party audits + Lloyd's-backed cover to $50M, ElevenLabs is a named policyholder; Armilla (affirmative AI cover + independent model verification, limits reported to $25M); Testudo (standalone Lloyd's-backed genAI policy to $10M, all 50 states); Klaimee (raised $5.5M July 2026 explicitly to insure autonomous AI agents, first- and third-party harm); plus Corgi, Vouch (affirmative AI E&O since Mar 2026), RiskCube, Relm. Registry/taxonomy side: AI Incident Database (~800-900 incidents, ~130-180/yr), OECD AI Incidents and Hazards Monitor (5,000-7,000 incident-reports via Event Registry), MIT AI Risk Repository (causal + domain taxonomies plus EU AI Act risk levels), AIAAIC. Even the actuarial method is published — arXiv 2606.16465 'Trace-Economic Underwriting', arXiv 2606.05449 'Insurance of Agentic AI', arXiv 2606.03777 CER framework. Market sizing is public (FactMR: $0.5B 2026 to $11.5B 2036, 36.8% CAGR), which is itself a crowding signal. | L12: The load-bearing claim — 'the acceptance side has no builder at all' — is false as of Aug 2026; AIUC/Armilla/Klaimee ARE the acceptor and each accretes its own claims data with privileged access an outsider cannot match. The why_now evidence is the weakest kind: five zero-star GitHub repos is a supply observation, not a demand trigger, and zero stars on issuance tooling says nothing about who wins on the underwriting side. Worse, a third-party registry cannot see closed claims — carriers own those and will not share them with a startup that plans to resell the aggregate. Seeding from 'publicly reported agent failures' just re-scrapes AIID and OECD AIM, which are free.
A13: regulated-gas-recovery-and-reclaim-ledger | B13: Licensed recovery and mass-balance ledger for phased-out high-GWP gases | C13: Search-backed | D13: 2 | E13: 8 | F13: 7 | G13: 6 | H13: 4 | I13: =ROUND(D13*Overview!$B$24+E13*Overview!$B$25+F13*Overview!$B$26+G13*Overview!$B$27+H13*Overview!$B$28,2) | J13: cut | K13: The claim 'no VC-backed company is visible' and 'there is no branded, contractor-facing collection network' is simply false — this is a mature industry with a public company in it. Refrigerant leg: Hudson Technologies (NASDAQ: HDSN) runs a named Refrigerant Buyback program, ships Cylinder QuickScan QR tracking (i.e. the cylinder-level ledger), does on-site recovery and system conversions, and acquired reclaimer Refrigerants Inc in December 2025 explicitly to expand access to field technicians and grow recovered volume — that is the exact roll-up thesis, already executing. A-Gas offers complete lifecycle buy/recover/reclaim/re-certify with a buyback program that manages all freight. American Refrigerants markets contractor buyback programs framed around the AIM Act by name. Golden Refrigerant and Tradewater are additional aggregators. SF6 leg: the mass-balance ledger has at least three shipping vendors — DILO Direct-Track (cloud, cylinder-to-switchgear, barcode scanning, automated compliance reporting with audit trails), EMT/Trakref SF6 Gas Management Software, and Concorde's ConcordeTrak. Recovery services: In-Gas Direct (recycling, disposal, reconditioning), Concorde Specialty Gases, Hitachi Power Solutions SF6 Gas Recovery Service, Schneider EcoFit Recover, RB Switchgear end-of-life services, Romu Keinänen (Finland), SF6 Relations, plus OEM service arms at ABB and Siemens. Nothing described here is unbuilt. | L13: Every date verifies — EU Reg 2024/573 bans SF6 in new MV switchgear ≤24kV from 1 Jan 2026, 52-145kV from 2028, 24-52kV from 2030, >145kV from 2032, general prohibition 2035; AIM Act cuts HFC allowances to 30% of baseline in 2029; recovery/reclaim/destruction by certified personnel is compulsory under the F-gas regime. The triggers are real and the opportunity is still dead, because the incumbents were built on exactly those dates and have processing plants, AHRI-700 certification, offtake contracts and cylinder fleets. A two-person entrant is a price-taking subcontractor to Hudson or A-Gas, not a consolidator: working capital is cylinders and gas inventory, the certification is a licence anyone can obtain rather than a moat, and the ledger software you would build after ten jobs is already given away by the cart manufacturer (DILO) to lock in equipment sales. Secondary risk: recovered-gas economics depend on the HFC price spread holding, and reclaimed product not counting against allowances draws exactly the well-capitalized competition already present.
... A78: einvoice-outage-durability-gateway | B78: Uptime as the product: continuity gateway for national e-invoicing rails | C78: Recall-only | D78: 2 | E78: 5 | F78: 8 | G78: 3 | H78: 2 | I78: =ROUND(D78*Overview!$B$24+E78*Overview!$B$25+F78*Overview!$B$26+G78*Overview!$B$27+H78*Overview!$B$28,2) | J78: cut | K78: The central factual claim is FALSIFIED by live GitHub code search. 'As of 2026-08-02 there are ZERO third-party products consuming [Latarnia]' is false — 111 code hits outside the MoF repo, including N1ebieski/ksef-php-client (90 stars) with a first-class Latarnia integration (src/Resources/Latarnia/LatarniaResource.php, Contracts/Resources/Latarnia/LatarniaResourceInterface.php, Requests/Latarnia/Status/StatusHandler.php and response fixtures), InPoint-Automation/Dolibarr-KSeF-Module (class/ksef_latarnia.class.php plus status.php), and blueshark-pl/faktury24-ksef (LatarniaKsefClient.php). Outage-feed consumption is already shipped in the leading community SDK and in a production ERP module. The related claim that 'all 22 KSeF repos are senders, viewers or gateways' is also wrong on count (567 hits; SDKs at 80-108 stars, an MCP server, agent skills). Structurally worse: Polish law mandates offline/awaria invoicing modes, so correct numbering, storage and back-filing are table stakes every compliant SDK, ERP and access point must implement — a feature, not a purchase. Pricing per invoice with an SLA puts you head-on against Comarch, Asseco, Sage and Symfonia domestically and Avalara/Sovos/Pagero globally, all of whom already bill per document and already own retry and reconciliation. CONFIRMED: CIRFMF/ksef-latarnia is real (16 stars, 27 open issues) and ksef-api carries 133 open issues today. | L78: Durability is a feature of an e-invoicing gateway, not a company — and the leading free SDK already ships the Latarnia client, so the wedge is gone before you start. The public status page is a giveaway with no conversion path, and any ERP that feels the pain adds an outbox in a sprint rather than routing every invoice through a startup.

Sheet Verification
A1: These objections were produced WITHOUT any live web search - the budget was exhausted before this stage ran. Verifiers were told to default to "refuted" on thin evidence, and the evidence was maximally thin, so the ~90% refutation rate is an artifact and does not discriminate between strong and weak ideas. Treat every row as a diligence question to answer, not a verdict to act on.
A3: ID | B3: Opportunity | C3: Refuted? | D3: Confidence | E3: Strongest objection | F3: What would have to be true | G3: What the verifier could actually check
